[
  {"name": "Adrahil I", "race": "Men", "culture": "Men of Gondor", "gender": "Male", "in_film": false},
  {"name": "Meldis", "race": "Men", "culture": "Edain", "gender": "Female", "in_film": false},
  {"name": "Goldilocks Gardner", "race": "Hobbit", "culture": "Shire-hobbits", "gender": "Female", "in_film": false},
  {"name": "Alfrid Lickspittle", "race": "Men", "culture": "Northmen of Rhovanion", "gender": "Male", "in_film": true},
  {"name": "Ufedhin", "race": "Elves", "culture": "Sindar", "gender": "Male", "in_film": false},
  {"name": "Balrog", "race": "Balrog", "culture": "Valaraukar", "gender": "Other", "in_film": true},
  {"name": "Nazgûl", "race": "Wraith", "culture": "Ringwraith", "gender": "Male", "in_film": true},
  {"name": "Durin", "race": "Dwarves", "culture": "Durin's Folk", "gender": "Male", "in_film": true},
  {"name": "Ents", "race": "Ents", "culture": "Fangorn", "gender": "Male", "in_film": true},
  {"name": "Entwives", "race": "Entwives", "culture": "NA", "gender": "Female", "in_film": true},
  {"name": "Figwit", "race": "Elves", "culture": "Elves of Rivendell", "gender": "Male", "in_film": true},
  {"name": "Fimbrethil", "race": "Entwives", "culture": "NA", "gender": "Female", "in_film": false},
  {"name": "Frodo Baggins", "race": "Hobbits", "culture": "Shire-hobbits", "gender": "Male", "in_film": true},
  {"name": "Ingwë", "race": "Elves", "culture": "Vanyar", "gender": "Male", "in_film": false},
  {"name": "Kíli", "race": "Dwarves", "culture": "Durin's Folk", "gender": "Male", "in_film": true},
  {"name": "Barney Butterbur", "race": "Hobbits", "culture": "Bree-hobbits", "gender": "Male", "in_film": true},
  {"name": "Merimac Brandybuck", "race": "Hobbits", "culture": "Shire-hobbits", "gender": "Male", "in_film": false},
  {"name": "Ar-Inziladûn", "race": "Men", "culture": "Númenóreans (House of Elros), The Faithful", "gender": "Male", "in_film": false}, {"name": "Azaghal", "race": "Dwarves", "culture": "Dwarves of Belegost (Broadbeams)", "gender": "Other", "in_film": false}, {"name": "Eothain", "race": "Men", "culture": "Rohirrim", "gender": "Other", "in_film": false}, {"name": "Eowyn", "race": "Men", "culture": "Rohirrim (House of Eorl)", "gender": "Other", "in_film": true}, {"name": "Grima Wormtongue", "race": "Men", "culture": "Rohirrim (Men of Rohan)", "gender": "Male", "in_film": true}, {"name": "Irimë", "race": "Elves", "culture": "Ñoldor (House of Finwë)", "gender": "Female", "in_film": false}, {"name": "Khîm", "race": "Dwarves", "culture": "Petty-Dwarves", "gender": "Male", "in_film": false}, {"name": "Lalaith", "race": "Men", "culture": "Edain (House of Hador), Men of Dor-lómin", "gender": "Female", "in_film": false}, {"name": "Magor", "race": "Men", "culture": "Edain (House of Marach)", "gender": "Male", "in_film": false}, {"name": "Míriel", "race": "Elves", "culture": "Ñoldor (House of Finwë)", "gender": "Female", "in_film": false}, {"name": "Rían", "race": "Men", "culture": "Edain (House of Bëor)Men of Dorthonion", "gender": "Other", "in_film": false}, {"name": "Sador", "race": "Men", "culture": "Edain (House of Hador)", "gender": "Male", "in_film": false}, {"name": "Túrin", "race": "Men", "culture": "Edain (House of Hador)", "gender": "Male", "in_film": false}, {"name": "Adalgrim Took", "race": "Hobbits", "culture": "Shire-hobbits (Took family)", "gender": "Male", "in_film": false}, {"name": "Adamanta (Chubb) Took", "race": "Hobbits", "culture": "Hobbit of the Shire (Took Family)", "gender": "Female", "in_film": false}, {"name": "Adanel", "race": "Men", "culture": "Edain (House of Marach)", "gender": "Female", "in_film": false}, {"name": "Adelard Took", "race": "Hobbits", "culture": "Shire-hobbits (Took family)", "gender": "Male", "in_film": false}, {"name": "Adrahil II", "race": "Men", "culture": "Dúnedain (House of Dol Amroth),  Men of Gondor", "gender": "Male", "in_film": false}, {"name": "Aegnor", "race": "Elves", "culture": "Ñoldor (House of Finarfin),Falmari (House of Olwë)", "gender": "Male", "in_film": false}, {"name": "Aelfwine", "race": "Man", "culture": "Mannish/Englishman", "gender": "Male", "in_film": false}, {"name": "Aerin", "race": "Men", "culture": "Edain (House of Hador), Men of Dor-lómin", "gender": "Female", "in_film": false}, {"name": "Ailinel", "race": "Men", "culture": "Númenóreans (House of Elros)", "gender": "Female", "in_film": false}, {"name": "Aiwendil", "race": "Ainur (Maiar)", "culture": "Istari (Wizards)Maiar of Yavanna", "gender": "Other", "in_film": true}, {"name": "Alatar", "race": "Ainur (Maiar)", "culture": "Istari (Wizards)", "gender": "Other", "in_film": false}, {"name": "Aldarion", "race": "Men", "culture": "Númenóreans (House of Elros)", "gender": "Male", "in_film": false}, {"name": "Aldor the Old", "race": "Men", "culture": "Rohirrim (House of Eorl)", "gender": "Male", "in_film": false}, {"name": "Algund", "race": "Men", "culture": "Edain (Men of Dor-lómin)", "gender": "Other", "in_film": false}, {"name": "Almarian", "race": "Men", "culture": "Númenórean", "gender": "Female", "in_film": false}, {"name": "Almiel", "race": "Men", "culture": "Númenóreans (House of Elros)", "gender": "Female", "in_film": false}, {"name": "Alphros", "race": "Men", "culture": "Dúnedain, Men of Gondor (House of Dol Amroth)", "gender": "Male", "in_film": false}, {"name": "Amandil", "race": "Men", "culture": "Númenóreans (House of Elros)The Faithful", "gender": "Male", "in_film": false}, {"name": "Amaranth Brandybuck", "race": "Hobbits", "culture": "Shire-hobbits (Brandybuck family)", "gender": "Female", "in_film": false}, {"name": "Amarië", "race": "Elves", "culture": "Vanyar", "gender": "Female", "in_film": false}, {"name": "Amdír", "race": "Elves", "culture": "Sindar, Elves of Doriath, Galadhrim", "gender": "Other", "in_film": false}, {"name": "Amlach", "race": "Men", "culture": "Edain", "gender": "Male", "in_film": false}, {"name": "Amras", "race": "Elves", "culture": "Ñoldor (House of Fëanor)", "gender": "Male", "in_film": false}, {"name": "Amrod", "race": "Elves", "culture": "Ñoldor (House of Fëanor)", "gender": "Other", "in_film": false}, {"name": "Amroth", "race": "Elves", "culture": "Sindar (Galadhrim) (Elves of Lórien)", "gender": "Other", "in_film": false}, {"name": "Amrothos", "race": "Men", "culture": "Dúnedain, Men of Gondor (House of Dol Amroth)", "gender": "Other", "in_film": false}, {"name": "Anairë", "race": "Elves", "culture": "Ñoldor (House of Fingolfin)", "gender": "Other", "in_film": false}, {"name": "Anborn", "race": "Men", "culture": "Dúnedain, Men of Gondor", "gender": "Other", "in_film": false}, {"name": "Ancalagon", "race": "Dragons", "culture": "Fire-drakes (Dragons of Morgoth)", "gender": "Other", "in_film": false}, {"name": "Ancalagon the Black", "race": "Dragons", "culture": "Fire-drakes (Dragons of Morgoth)", "gender": "Other", "in_film": false}, {"name": "Andreth", "race": "Men", "culture": "Edain (House of Bëor)", "gender": "Female", "in_film": false}, {"name": "Andróg", "race": "Men", "culture": "Edain, Men of Dor-lómin", "gender": "Male", "in_film": false}, {"name": "Angaráto", "race": "Elves", "culture": "Ñoldor (House of Finarfin)Falmari (House of Olwë)", "gender": "Other", "in_film": false}, {"name": "Angelica Baggins", "race": "Hobbit", "culture": "Shire-Hobbits", "gender": "Other", "in_film": false}, {"name": "Angelimir", "race": "Men", "culture": "Dúnedain (House of Dol Amroth), Men of Gondor", "gender": "Male", "in_film": false}, {"name": "Angrod", "race": "Elves", "culture": "Ñoldor (House of Finarfin)Falmari (House of Olwë)", "gender": "Other", "in_film": false}, {"name": "Annael", "race": "Elves", "culture": "Sindar, Elves of Mithrim", "gender": "Male", "in_film": false}, {"name": "Anárion", "race": "Men", "gender": "Other", "in_film": false}, {"name": "Ar-Adûnakhôr", "race": "Men", "culture": "Númenórean (House of Elros), King's Men", "gender": "Male", "in_film": false}, {"name": "Ar-Gimilzôr", "race": "Men", "culture": "Númenóreans (King's Men)", "gender": "Male", "in_film": false}, {"name": "Ar-Pharazon", "race": "Men", "culture": "Númenóreans (King's Men), House of Elros", "gender": "Male", "in_film": false}, {"name": "Ar-Pharazôn", "race": "Men", "culture": "Númenóreans (King's Men), House of Elros", "gender": "Male", "in_film": false}, {"name": "Ar-Sakalthôr", "race": "Men", "culture": "Númenóreans, King's Men", "gender": "Male", "in_film": false}, {"name": "Ar-Zimrathôn", "race": "Men", "culture": "Númenórean (House of Elros), King's Men", "gender": "Male", "in_film": false}, {"name": "Arador", "race": "Men", "culture": "Dúnedain of the North, (House of Isildur), Rangers of the North", "gender": "Male", "in_film": false}, {"name": "Arafinwë", "race": "Elves", "culture": "Ñoldor (House of Finwë)", "gender": "Male", "in_film": false}, {"name": "Araglas", "race": "Men", "culture": "Dúnedain of the North (House of Isildur), Rangers of the North", "gender": "Male", "in_film": false}, {"name": "Aragorn", "race": "Men", "culture": "Dúnedain of the North (House of Isildur, founded the House of Telcontar)", "gender": "Other", "in_film": true}, {"name": "Aragost", "race": "Men", "culture": "Dúnedain of the North (House of Isildur), Rangers of the North", "gender": "Male", "in_film": false}, {"name": "Arahad II", "race": "Men", "culture": "Dúnedain of the North (House of Isildur), Rangers of the North", "gender": "Male", "in_film": false}, {"name": "Arahael", "race": "Men", "culture": "Dúnedain of the North (Rangers of the North)", "gender": "Male", "in_film": false}, {"name": "Aranarth", "race": "Men", "culture": "Dúnedain of the North (House of Isildur), Rangers of the North", "gender": "Male", "in_film": false}, {"name": "Arantar", "race": "Men", "culture": "Dúnedain of the North (House of Isildur)", "gender": "Male", "in_film": false}, {"name": "Aranwë", "race": "Elves", "culture": "Ñoldor (House of Fingolfin), Gondolindrim", "gender": "Male", "in_film": false}, {"name": "Araphant", "race": "Men", "culture": "Dúnedain of the North (House of Isildur)", "gender": "Male", "in_film": false}, {"name": "Araphor", "race": "Men", "culture": "Dúnedain of the North (House of Isildur)", "gender": "Male", "in_film": false}, {"name": "Arassuil", "race": "Men", "culture": "Dúnedain of the North (House of Isildur), Rangers of the North", "gender": "Male", "in_film": false}, {"name": "Aratan", "race": "Men", "culture": "Dúnedain (House of Isildur)", "gender": "Other", "in_film": false}, {"name": "Arathorn", "race": "Men", "culture": "Dúnedain of the North (Rangers of the North)", "gender": "Male", "in_film": false}, {"name": "Arathorn II", "race": "Men", "culture": "Dúnedain of the North (Rangers of the North)", "gender": "Male", "in_film": false}, {"name": "Araval", "race": "Men", "culture": "Dúnedain of the North (House of Isildur)", "gender": "Male", "in_film": false}, {"name": "Aravir", "race": "Men", "culture": "Dúnedain of the North (Rangers of the North)", "gender": "Male", "in_film": false}, {"name": "Aravorn", "race": "Men", "culture": "Dúnedain of the North (House of Isildur), Rangers of the North", "gender": "Male", "in_film": false}, {"name": "Aredhel", "race": "Elves", "culture": "Ñoldor (House of Fingolfin)Gondolindrim", "gender": "Other", "in_film": false}, {"name": "Argeleb I", "race": "Men", "culture": "Dúnedain of the North (House of Isildur)", "gender": "Male", "in_film": false}, {"name": "Argeleb II", "race": "Men", "culture": "Dúnedain of the North (House of Isildur)", "gender": "Male", "in_film": false}, {"name": "Argon", "race": "Elves", "culture": "Ñoldor (House of Fingolfin)", "gender": "Male", "in_film": false}, {"name": "Argonui", "race": "Men", "culture": "Dúnedain of the North (House of Isildur), Rangers of the North", "gender": "Male", "in_film": false}, {"name": "Arien", "race": "Ainur", "culture": "Maiar of Vána", "gender": "Female", "in_film": false}, {"name": "Arminas", "race": "Elves", "culture": "Ñoldor (House of Finarfin)Elves of DorthonionElves of the Havens of Sirion", "gender": "Male", "in_film": false}, {"name": "Arod", "race": "Horses", "gender": "Male", "in_film": true}, {"name": "Arvedui", "race": "Men", "culture": "Dúnedain of the North (House of Isildur)", "gender": "Other", "in_film": false}, {"name": "Arvegil", "race": "Men", "culture": "Dúnedain of the North (House of Isildur)", "gender": "Male", "in_film": false}, {"name": "Arveleg I", "race": "Men", "culture": "Dúnedain of the North (House of Isildur)", "gender": "Other", "in_film": false}, {"name": "Arveleg II", "race": "Men", "culture": "Dúnedain of the North (House of Isildur)", "gender": "Male", "in_film": false}, {"name": "Arwen", "race": "Half-elven", "culture": "Elves of Lindon,Elves of Rivendell", "gender": "Other", "in_film": true}, {"name": "Arwen Evenstar", "race": "Half-elven", "culture": "Elves of Lindon,Elves of Rivendell", "gender": "Other", "in_film": true}, {"name": "Arwen Undómiel", "race": "Half-elven", "culture": "Elves of Lindon,Elves of Rivendell", "gender": "Other", "in_film": true}, {"name": "Asfaloth", "race": "Horses", "culture": "Horses of Rivendell", "gender": "Male", "in_film": true}, {"name": "Atanalcar", "race": "Men", "culture": "Númenóreans (House of Elros)", "gender": "Male", "in_film": false}, {"name": "Aule", "race": "Ainur", "culture": "Valar (Aratar)", "gender": "Other", "in_film": false}, {"name": "Aulë", "race": "Ainur", "culture": "Valar (Aratar)", "gender": "Other", "in_film": false}, {"name": "Axantur", "race": "Men", "culture": "Númenóreans (House of Elros)", "gender": "Male", "in_film": false}, {"name": "Azaghâl", "race": "Dwarves", "culture": "Dwarves of Belegost (Broadbeams)", "gender": "Other", "in_film": false}, {"name": "Azog", "race": "Orcs", "culture": "Moria Orcs", "gender": "Other", "in_film": true}, {"name": "Bain", "race": "Men", "culture": "Men of Dale", "gender": "Other", "in_film": true}, {"name": "Balbo Baggins", "race": "Hobbits", "culture": "Shire-hobbits (Baggins family)", "gender": "Male", "in_film": false}, {"name": "Balin", "race": "Dwarves", "culture": "Durin's Folk", "gender": "Other", "in_film": true}, {"name": "Bandobras Took", "race": "Hobbit", "culture": "Shire-hobbit (Took family)", "gender": "Other", "in_film": true}, {"name": "Baragund", "race": "Men", "culture": "Edain (House of Bëor), Men of Dorthonion", "gender": "Male", "in_film": false}, {"name": "Barahir", "race": "Men", "culture": "Edain (House of Bëor)Men of Dorthonion", "gender": "Male", "in_film": false}, {"name": "Baran", "race": "Men", "culture": "Edain (House of Bëor), Men of Estolad", "gender": "Male", "in_film": false}, {"name": "Baranor", "race": "Men", "culture": "Edain (House of Bëor)", "gender": "Male", "in_film": false}, {"name": "Bard", "race": "Men", "culture": "Men of Lake-town, Men of Dale", "gender": "Male", "in_film": true}, {"name": "Bard the Bowman", "race": "Men", "culture": "Men of Lake-town, Men of Dale", "gender": "Male", "in_film": true}, {"name": "Barliman Butterbur", "race": "Men", "culture": "Men of Bree", "gender": "Other", "in_film": true}, {"name": "Beldis", "race": "Men", "culture": "Edain (House of Bëor)", "gender": "Female", "in_film": false}, {"name": "Beleg", "race": "Elves", "culture": "Sindar (Elves of Doriath)", "gender": "Male", "in_film": false}, {"name": "Beleg Cúthalion", "race": "Elves", "culture": "Sindar (Elves of Doriath)", "gender": "Male", "in_film": false}, {"name": "Belegund", "race": "Men", "culture": "Edain (House of Bëor), Men of Dorthonion", "gender": "Male", "in_film": false}, {"name": "Belemir", "race": "Men", "culture": "Edain (House of Bëor)", "gender": "Male", "in_film": false}, {"name": "Belen", "race": "Men", "culture": "Edain (House of Bëor)Men of Estolad", "gender": "Male", "in_film": false}, {"name": "Belladonna Took", "race": "Hobbits", "culture": "Shire-hobbits", "gender": "Female", "in_film": true}, {"name": "Beorn", "race": "Man (Skin-changer)", "culture": "Beornings", "gender": "Other", "in_film": true}, {"name": "Bereg", "race": "Men", "culture": "Edain (House of Bëor)", "gender": "Male", "in_film": false}, {"name": "Beregond", "race": "Men", "culture": "Men of Gondor (House of Húrin)", "gender": "Male", "in_film": false}, {"name": "Beren", "race": "Men", "culture": "Edain (House of Bëor)", "gender": "Other", "in_film": false}, {"name": "Beren Erchamion", "race": "Men", "culture": "Edain (House of Bëor)", "gender": "Other", "in_film": false}, {"name": "Bergil", "race": "Men", "culture": "Men of Gondor (House of Baranor)", "gender": "Male", "in_film": false}, {"name": "Berúthiel", "race": "Men", "culture": "Dúnedain (Black Númenórean)Men of Gondor", "gender": "Female", "in_film": false}, {"name": "Bifur", "race": "Dwarves", "culture": "Dwarves of Khazad-dûm", "gender": "Other", "in_film": true}, {"name": "Bilbo", "race": "Hobbits", "culture": "Shire-hobbits (Baggins family)", "gender": "Other", "in_film": true}, {"name": "Bilbo Baggins", "race": "Hobbits", "culture": "Shire-hobbits (Baggins family)", "gender": "Other", "in_film": true}, {"name": "Bilbo Gamgee", "race": "Hobbit", "culture": "Shire-hobbits (Gamgee family, Gardner family)", "gender": "Male", "in_film": false}, {"name": "Bilbo Gardner", "race": "Hobbit", "culture": "Shire-hobbits (Gamgee family, Gardner family)", "gender": "Male", "in_film": false}, {"name": "Bill Ferny", "race": "Men", "culture": "Men of Bree", "gender": "Other", "in_film": true}, {"name": "Blanco", "race": "Hobbits", "culture": "Fallohide-hobbits", "gender": "Male", "in_film": false}, {"name": "Blanco Bracegirdle", "race": "Hobbits", "culture": "Shire-hobbits (Bracegirdle family)", "gender": "Male", "in_film": false}, {"name": "Bob", "race": "Hobbits", "culture": "Hobbits of Bree", "gender": "Male", "in_film": false}, {"name": "Bofur", "race": "Dwarves", "culture": "Unknown; possibly Firebeards or Broadbeams", "gender": "Male", "in_film": true}, {"name": "Bolg", "race": "Goblin/Orc", "culture": "Orcs of Moria", "gender": "Male", "in_film": true}, {"name": "Bombur", "race": "Dwarves", "culture": "Unknown; possibly Firebeards or Broadbeams", "gender": "Other", "in_film": true}, {"name": "Bor", "race": "Men", "culture": "Faithful Easterlings", "gender": "Male", "in_film": false}, {"name": "Borin", "race": "Dwarven", "culture": "Durin's Folk", "gender": "Male", "in_film": false}, {"name": "Borlach", "race": "Men", "culture": "Easterlings (Easterlings of Lothlann)", "gender": "Male", "in_film": false}, {"name": "Borlas", "race": "Men", "culture": "Men of Gondor", "gender": "Male", "in_film": true}, {"name": "Boromir", "race": "Men", "culture": "Men of Gondor (House of Húrin)", "gender": "Male", "in_film": true}, {"name": "Brand", "race": "Men", "culture": "Men of Dale", "gender": "Other", "in_film": false}, {"name": "Brandir", "race": "Men", "culture": "Edain (House of Haleth)", "gender": "Other", "in_film": false}, {"name": "Brego", "race": "Men", "culture": "Rohirrim (House of Eorl)", "gender": "Male", "in_film": false}, {"name": "Bregolas", "race": "Men", "culture": "Edain (House of Bëor)", "gender": "Male", "in_film": false}, {"name": "Bregor", "race": "Men", "culture": "Edain (House of Bëor), Men of Dorthonion", "gender": "Male", "in_film": false}, {"name": "Brodda", "race": "Men", "culture": "Easterlings", "gender": "Male", "in_film": false}, {"name": "Bruno Bracegirdle", "race": "Hobbits", "culture": "Shire-hobbits (Bracegirdles)", "gender": "Male", "in_film": false}, {"name": "Bungo Baggins", "race": "Hobbit", "culture": "Shire-hobbit", "gender": "Male", "in_film": false}, {"name": "Bëor", "race": "Men", "culture": "Edain (House of Bëor)Men of Estolad", "gender": "Male", "in_film": false}, {"name": "Caranthir", "race": "Elves", "culture": "Ñoldor (House of Fëanor)", "gender": "Male", "in_film": false}, {"name": "Carc", "race": "Raven", "gender": "Male", "in_film": false}, {"name": "Carcharoth", "race": "Werewolves", "culture": "Werewolves (Children of Draugluin)", "gender": "Other", "in_film": false}, {"name": "Castamir", "race": "Men", "culture": "Dúnedain (House of Anárion), Men of Gondor", "gender": "Male", "in_film": false}, {"name": "Celandine Brandybuck", "race": "Hobbits", "culture": "Shire-hobbits (Brandybucks)", "gender": "Female", "in_film": false}, {"name": "Celeborn", "race": "Elves", "culture": "Sindar (Elves of Doriath)", "gender": "Male", "in_film": true}, {"name": "Celebrian", "race": "Elves", "culture": "Falmari (House of Olwë),Sindar (House of Celeborn),Ñoldor (House of Finarfin),Elves of Rivendell,Galadhrim,Elves of Eregion", "gender": "Female", "in_film": false}, {"name": "Celebrimbor", "race": "Elves", "culture": "Ñoldor (House of Fëanor),Elves of Eregion (Gwaith-i-Mírdain)", "gender": "Male", "in_film": false}, {"name": "Celebrían", "race": "Elves", "culture": "Falmari (House of Olwë),Sindar (House of Celeborn),Ñoldor (House of Finarfin),Elves of Rivendell,Galadhrim,Elves of Eregion", "gender": "Female", "in_film": false}, {"name": "Celegorm", "race": "Elves", "culture": "Ñoldor (House of Fëanor)", "gender": "Male", "in_film": false}, {"name": "Celepharn", "race": "Men", "culture": "Dúnedain of the North (House of Isildur)", "gender": "Male", "in_film": false}, {"name": "Cemendur", "race": "Men", "culture": "DúnedainMen of Gondor (House of Anárion)", "gender": "Other", "in_film": false}, {"name": "Cirdan", "race": "Elves", "culture": "Sindar", "gender": "Other", "in_film": true}, {"name": "Cirion", "race": "Men", "culture": "Men of Gondor (House of Húrin)", "gender": "Male", "in_film": false}, {"name": "Ciryatur", "race": "Men", "culture": "Númenóreans", "gender": "Male", "in_film": false}, {"name": "Ciryon", "race": "Men", "culture": "Dúnedain (House of Isildur)", "gender": "Male", "in_film": false}, {"name": "Curufin", "race": "Elves", "culture": "Ñoldor (House of Fëanor)", "gender": "Other", "in_film": false}, {"name": "Curufinwë", "race": "Elves", "culture": "Ñoldor (House of Finwë)", "gender": "Other", "in_film": false}, {"name": "Curumo", "race": "Ainur", "culture": "Maiar of Aulë (Wizards)", "gender": "Male", "in_film": true}, {"name": "Curunír", "race": "Ainur", "culture": "Maiar of Aulë (Wizards)", "gender": "Male", "in_film": true}, {"name": "Círdan", "race": "Elves", "culture": "Sindar", "gender": "Other", "in_film": true}, {"name": "Daddy Twofoot", "race": "Hobbit", "culture": "Shire-hobbits", "gender": "Other", "in_film": false}, {"name": "Daeron", "race": "Elves", "culture": "Sindar, Elves of Doriath, Lambengolmor", "gender": "Other", "in_film": false}, {"name": "Dain II Ironfoot", "race": "Dwarves", "culture": "Durin's Folk (Dwarves of the Iron Hills)", "gender": "Male", "in_film": true}, {"name": "Dain Ironfoot", "race": "Dwarves", "culture": "Durin's Folk (Dwarves of the Iron Hills)", "gender": "Male", "in_film": true}, {"name": "Daisy Gamgee", "race": "Hobbits", "gender": "Female", "in_film": false}, {"name": "Damrod", "race": "Men", "culture": "Dúnedain, Men of Gondor", "gender": "Other", "in_film": true}, {"name": "Denethor", "race": "Men", "culture": "Men of Gondor (House of Húrin)", "gender": "Other", "in_film": true}, {"name": "Denethor II", "race": "Men", "culture": "Men of Gondor (House of Húrin)", "gender": "Other", "in_film": true}, {"name": "Derufin", "race": "Men", "culture": "Men of Gondor", "gender": "Male", "in_film": true}, {"name": "Dervorin", "race": "Men", "culture": "Dúnedain, Men of Gondor", "gender": "Other", "in_film": false}, {"name": "Diamond Took", "race": "Hobbits", "culture": "Shire-hobbit", "gender": "Female", "in_film": true}, {"name": "Diamond of Long Cleeve", "race": "Hobbits", "culture": "Shire-hobbit", "gender": "Female", "in_film": true}, {"name": "Dinodas Brandybuck", "race": "Hobbits", "culture": "Shire-hobbits, Bucklanders (Brandybuck)", "gender": "Male", "in_film": false}, {"name": "Dior", "race": "Half-elven", "culture": "House of Bëor", "gender": "Male", "in_film": false}, {"name": "Dior Eluchil", "race": "Half-elven", "culture": "House of Bëor", "gender": "Male", "in_film": false}, {"name": "Dirhael", "race": "Men", "culture": "Dúnedain of the North (House of Isildur), Rangers of the North", "gender": "Male", "in_film": false}, {"name": "Dis", "race": "Dwarves", "culture": "Durin's Folk,Dwarves of the Lonely Mountain", "gender": "Female", "in_film": false}, {"name": "Dodinas Brandybuck", "race": "Hobbits", "culture": "Shire-hobbits, Bucklanders (Brandybuck", "gender": "Male", "in_film": false}, {"name": "Donnamira Took", "race": "Hobbits", "culture": "Shire-hobbits (Tooks & Boffins)", "gender": "Female", "in_film": false}, {"name": "Dori", "race": "Dwarves", "culture": "Durin's Folk", "gender": "Male", "in_film": true}, {"name": "Dorlas", "race": "Men", "culture": "Edain (House of Haleth), Men of Brethil", "gender": "Males", "in_film": false}, {"name": "Draugluin", "race": "Werewolves", "culture": "Wolves of Angband", "gender": "Male", "in_film": false}, {"name": "Drogo Baggins", "race": "Hobbits", "culture": "Shire-hobbits (Baggins family)", "gender": "Male", "in_film": false}, {"name": "Dudo Baggins", "race": "Hobbits", "culture": "Shire-hobbits (Baggins family)", "gender": "Male", "in_film": false}, {"name": "Duilin", "race": "Men", "culture": "Men of Gondor", "gender": "Male", "in_film": false}, {"name": "Duinhir", "race": "Men", "culture": "Men of Gondor", "gender": "Male", "in_film": false}, {"name": "Dwalin", "race": "Dwarves", "culture": "Durin's Folk", "gender": "Male", "in_film": true}, {"name": "Dáin Ironfoot", "race": "Dwarves", "culture": "Durin's Folk (Dwarves of the Iron Hills)", "gender": "Male", "in_film": true}, {"name": "Déagol", "race": "Hobbits", "culture": "Stoor-hobbits of the Gladden Fields", "gender": "Other", "in_film": true}, {"name": "Dírhael", "race": "Men", "culture": "Dúnedain of the North (House of Isildur), Rangers of the North", "gender": "Male", "in_film": false}, {"name": "Dírhavel", "race": "Men", "culture": "Edain (House of Hador)", "gender": "Male", "in_film": false}, {"name": "Dís", "race": "Dwarves", "culture": "Durin's Folk,Dwarves of the Lonely Mountain", "gender": "Female", "in_film": false}, {"name": "Earendil", "race": "Half-elven", "culture": "Gondolindrim,Elves of the Havens of Sirion", "gender": "Male", "in_film": false}, {"name": "Ecthelion II", "race": "Men", "culture": "Men of Gondor (House of Húrin)", "gender": "Male", "in_film": false}, {"name": "Ecthelion of the Fountain", "race": "Elves", "culture": "Ñoldor, Gondolindrim (House of the Fountain)", "gender": "Male", "in_film": false}, {"name": "Edrahil", "race": "Elf", "culture": "High Elves, Noldor", "gender": "Male", "in_film": false}, {"name": "Egalmoth", "race": "Men", "culture": "Men of Gondor  (House of Húrin)", "gender": "Male", "in_film": false}, {"name": "Eglantine Banks", "race": "Hobbits", "culture": "Shire-hobbits (Banks), (Took family)", "gender": "Female", "in_film": false}, {"name": "Eglantine Took", "race": "Hobbits", "culture": "Shire-hobbits (Banks), (Took family)", "gender": "Female", "in_film": false}, {"name": "Eilinel", "race": "Men", "culture": "Edain", "gender": "Female", "in_film": false}, {"name": "Elanor Gamgee", "race": "Hobbits", "culture": "Shire-hobbits (Gamgee family, Gardner family & Fairbairn family)", "gender": "Female", "in_film": true}, {"name": "Elanor Gardner", "race": "Hobbits", "culture": "Shire-hobbits (Gamgee family, Gardner family & Fairbairn family)", "gender": "Female", "in_film": true}, {"name": "Elanor the Fair", "race": "Hobbits", "culture": "Shire-hobbits (Gamgee family, Gardner family & Fairbairn family)", "gender": "Female", "in_film": true}, {"name": "Elatan", "race": "Men", "culture": "Númenóreans", "gender": "Male", "in_film": false}, {"name": "Elbereth Gilthoniel", "race": "Ainur", "culture": "Valar (Aratar) (Leader, Queen)", "gender": "Other", "in_film": false}, {"name": "Elboron", "race": "Men", "culture": "Men of Gondor (House of Húrin)", "gender": "Male", "in_film": false}, {"name": "Eldacar of Gondor", "race": "Men", "culture": "Northmen,Men of Gondor", "gender": "Male", "in_film": false}, {"name": "Eldalótë", "race": "Elves", "culture": "Ñoldor (House of Finwë)", "gender": "Female", "in_film": false}, {"name": "Eldarion", "race": "Half-elven", "culture": "Dúnedain (House of Telcontar)", "gender": "Other", "in_film": true}, {"name": "Elemmakil", "race": "Elves", "culture": "ÑoldorGondolindrim", "gender": "Male", "in_film": false}, {"name": "Elendil", "race": "Men", "culture": "Faithful Númenoreans (Lords of Andúnië)", "gender": "Other", "in_film": true}, {"name": "Elendur", "race": "Men", "culture": "Númenóreans (The Faithful), Dúnedain of the North", "gender": "Other", "in_film": false}, {"name": "Elenwë", "race": "Elves", "culture": "Vanyar (Elves of Valinor)", "gender": "Female", "in_film": false}, {"name": "Elfhelm", "race": "Men", "culture": "Rohirrim", "gender": "Male", "in_film": false}, {"name": "Elfhild", "race": "Men", "culture": "Rohirrim (House of Eorl)", "gender": "Female", "in_film": false}, {"name": "Elfstan Fairbairn", "race": "Hobbits", "culture": "Shire-hobbits (Fairbairns)", "gender": "Male", "in_film": false}, {"name": "Elfwine", "race": "Men", "culture": "Rohirrim (House of Eorl)", "gender": "Other", "in_film": false}, {"name": "Elladan", "race": "Elves", "culture": "Half-elven (Elves of Rivendell)", "gender": "Male", "in_film": true}, {"name": "Elladan and Elrohir", "race": "Elves", "culture": "Half-elven (Elves of Rivendell)", "gender": "Male", "in_film": true}, {"name": "Elmo", "race": "Elves", "culture": "Sindar (House of Elmo)", "gender": "Male", "in_film": false}, {"name": "Elphir", "race": "Men", "culture": "Dúnedain, Men of Gondor (House of Dol Amroth)", "gender": "Male", "in_film": false}, {"name": "Elrohir", "race": "Elves", "culture": "Half-elven (Elves of Rivendell)", "gender": "Male", "in_film": true}, {"name": "Elrond", "race": "Half-elven", "gender": "Other", "in_film": true}, {"name": "Elros", "race": "Half-elven (chose to be mortal)", "culture": "Ñoldor (House of Fingolfin), Sindar (House of Thingol)Dúnedain of Númenor (House of Elros)", "gender": "Other", "in_film": false}, {"name": "Elu Thingol", "race": "Elves", "culture": "Teleri (Sindar)(House of Thingol)Elves of Doriath", "gender": "Other", "in_film": false}, {"name": "Elurin", "race": "Half-elven", "culture": "House of Bëor", "gender": "Male", "in_film": false}, {"name": "Eluréd", "race": "Half-elven", "culture": "House of Bëor", "gender": "Male", "in_film": false}, {"name": "Eluréd and Elurín", "race": "Half-elven", "culture": "House of Bëor", "gender": "Male", "in_film": false}, {"name": "Elurín", "race": "Half-elven", "culture": "House of Bëor", "gender": "Male", "in_film": false}, {"name": "Elwing", "race": "Half-elven (chose to be immortal)", "culture": "Sindar of Doriath (House of Thingol)", "gender": "Other", "in_film": false}, {"name": "Elwë", "race": "Elves", "culture": "Teleri (Sindar)(House of Thingol)Elves of Doriath", "gender": "Other", "in_film": false}, {"name": "Emeldir", "race": "Men", "culture": "Edain (House of Bëor)Men of Dorthonion, later Men of Brethil", "gender": "Female", "in_film": false}, {"name": "Enel", "race": "Elves", "culture": "Nelyar-elves", "gender": "Male", "in_film": false}, {"name": "Enelyë", "race": "Elves", "culture": "Nelyar-elves", "gender": "Female", "in_film": false}, {"name": "Enerdhil", "race": "Elves", "culture": "Ñoldor, Gondolindrim", "gender": "Male", "in_film": false}, {"name": "Eomer", "race": "Men", "culture": "Rohirrim (House of Eorl)", "gender": "Other", "in_film": true}, {"name": "Eonwe", "race": "Ainur", "culture": "Maiar", "gender": "Male", "in_film": false}, {"name": "Eorl", "race": "Men", "culture": "Éothéod,Rohirrim", "gender": "Male", "in_film": false}, {"name": "Eorl the Young", "race": "Men", "culture": "Éothéod,Rohirrim", "gender": "Male", "in_film": false}, {"name": "Eradan", "race": "Men", "culture": "Men of Gondor (House of Húrin)", "gender": "Male", "in_film": false}, {"name": "Erchirion", "race": "Men", "culture": "Dúnedain, Men of Gondor (House of Dol Amroth)", "gender": "Male", "in_film": false}, {"name": "Ereinion", "race": "Elves", "culture": "Ñoldor (House of Fingolfin) (The Silmarillion)Ñoldor (House of Finarfin), Falmari (House of Olwë) (later notes)", "gender": "Other", "in_film": true}, {"name": "Erellont", "race": "Elves", "culture": "Elves of Beleriand", "gender": "Male", "in_film": false}, {"name": "Erendis", "race": "Men", "culture": "Númenóreans (House of Elros)", "gender": "Female", "in_film": false}, {"name": "Erestor", "race": "Elves", "culture": "Elves of Rivendell", "gender": "Male", "in_film": true}, {"name": "Eriol", "race": "Man", "culture": "Mannish/Englishman", "gender": "Male", "in_film": false}, {"name": "Eru", "race": "God", "gender": "Other", "in_film": false}, {"name": "Eru Illuvatar", "race": "God", "gender": "Other", "in_film": false}, {"name": "Eru Ilúvatar", "race": "God", "gender": "Other", "in_film": false}, {"name": "Esmeralda Brandybuck", "race": "Hobbits", "culture": "Shire-hobbits (Took family) & (Brandybuck family)", "gender": "Female", "in_film": false}, {"name": "Esmeralda Took", "race": "Hobbits", "culture": "Shire-hobbits (Took family) & (Brandybuck family)", "gender": "Female", "in_film": false}, {"name": "Estë", "race": "Ainur", "culture": "Valar", "gender": "Female", "in_film": false}, {"name": "Everard Took", "race": "Hobbits", "culture": "Shire-hobbits (Took family)", "gender": "Male", "in_film": false}, {"name": "Eärendil", "race": "Half-elven", "culture": "Gondolindrim,Elves of the Havens of Sirion", "gender": "Male", "in_film": false}, {"name": "Eärendil the Mariner", "race": "Half-elven", "culture": "Gondolindrim,Elves of the Havens of Sirion", "gender": "Male", "in_film": false}, {"name": "Eärnil II", "race": "Men", "culture": "Dúnedain, Men of Gondor (House of Anárion)", "gender": "Male", "in_film": false}, {"name": "Eärnur", "race": "Men", "culture": "DúnedainMen of Gondor (House of Anárion)", "gender": "Other", "in_film": false}, {"name": "Eärwen", "race": "Elves", "culture": "Falmari (House of Olwë)", "gender": "Other", "in_film": false}, {"name": "Eöl", "race": "Elves", "culture": "Avari (Moriquendi), Úmanyar (Sindar), Elves of Nan Elmoth", "gender": "Male", "in_film": false}, {"name": "Eönwë", "race": "Ainur", "culture": "Maiar", "gender": "Male", "in_film": false}, {"name": "Faramir", "race": "Men", "culture": "Men of Gondor (House of Húrin)", "gender": "Other", "in_film": true}, {"name": "Faramir Took", "race": "Hobbits", "culture": "Shire-hobbits (Took family)", "gender": "Male", "in_film": false}, {"name": "Faramir son of Ondoher", "race": "Men", "culture": "Men of Gondor (House of Anárion)", "gender": "Male", "in_film": false}, {"name": "Farin", "race": "Dwarves", "culture": "Durin's Folk, Dwarves of the Grey Mountains, Dwarves of the Lonely Mountain, Dwarves of Thorin's Halls", "gender": "Male", "in_film": false}, {"name": "Farmer Cotton", "race": "Hobbits", "culture": "Shire-hobbits (Cotton family)", "gender": "Male", "in_film": false}, {"name": "Farmer Maggot", "race": "Hobbits", "culture": "Shire-hobbit (Maggot family)", "gender": "Other", "in_film": true}, {"name": "Fatty Bolger", "race": "Hobbits", "culture": "Shire-hobbits (Bolger family)", "gender": "Male", "in_film": true}, {"name": "Feanor", "race": "Elves", "culture": "Ñoldor (House of Finwë)", "gender": "Other", "in_film": false}, {"name": "Fengel", "race": "Men", "culture": "Rohirrim (House of Eorl)", "gender": "Other", "in_film": false}, {"name": "Ferumbras Took II", "race": "Hobbits", "culture": "Hobbit of Tookland (Took Family)", "gender": "Male", "in_film": false}, {"name": "Ferumbras Took III", "race": "Hobbits", "culture": "Shire-hobbits (Took family)", "gender": "Male", "in_film": false}, {"name": "Fili", "race": "Dwarves", "culture": "Durin's Folk", "gender": "Other", "in_film": true}, {"name": "Finarfin", "race": "Elves", "culture": "Ñoldor (House of Finwë)", "gender": "Male", "in_film": false}, {"name": "Findegil", "race": "Men", "culture": "Men of Gondor", "gender": "Male", "in_film": false}, {"name": "Findis", "race": "Elves", "culture": "Ñoldor (House of Finwë)", "gender": "Female", "in_film": false}, {"name": "Finduilas", "race": "Elves", "culture": "Ñoldor (House of Finarfin), Northern Sindar, Falmari (House of Olwë)", "gender": "Other", "in_film": false}, {"name": "Finduilas of Dol Amroth", "race": "Men", "culture": "Dúnedain (House of Dol Amroth)", "gender": "Female", "in_film": false}, {"name": "Finglas", "race": "Ent", "gender": "Other", "in_film": false}, {"name": "Fingolfin", "race": "Elves", "culture": "Ñoldor (House of Finwë)", "gender": "Male", "in_film": false}, {"name": "Fingon", "race": "Elves", "culture": "Ñoldor (House of Fingolfin)", "gender": "Male", "in_film": false}, {"name": "Finrod", "race": "Elves", "culture": "Ñoldor (House of Finarfin),Falmari (House of Olwë),Elves of Nargothrond", "gender": "Male", "in_film": false}, {"name": "Finrod Felagund", "race": "Elves", "culture": "Ñoldor (House of Finarfin),Falmari (House of Olwë),Elves of Nargothrond", "gender": "Male", "in_film": false}, {"name": "Finwë", "race": "Elves", "culture": "Ñoldor (House of Finwë)", "gender": "Male", "in_film": false}, {"name": "Flói", "race": "Dwarves", "culture": "Durin's Folk", "gender": "Male", "in_film": false}, {"name": "Folca", "race": "Men", "culture": "Rohirrim (House of Eorl)", "gender": "Male", "in_film": false}, {"name": "Folco Boffin", "race": "Hobbits", "culture": "Shire-hobbits", "gender": "Male", "in_film": true}, {"name": "Forlong", "race": "Men", "culture": "Men of Gondor", "gender": "Male", "in_film": false}, {"name": "Fortinbras Took I", "race": "Hobbits", "culture": "Hobbit of Tookland (Took Family)", "gender": "Male", "in_film": false}, {"name": "Fortinbras Took II", "race": "Hobbits", "culture": "Shire-hobbits (Took family)", "gender": "Male", "in_film": false}, {"name": "Fosco Baggins", "race": "Hobbits", "culture": "Shire-hobbits (Baggins family)", "gender": "male", "in_film": false}, {"name": "Fram", "race": "Men", "culture": "Éothéod", "gender": "Male", "in_film": false}, {"name": "Frar", "race": "Dwarf", "culture": "Durin's Folk", "gender": "Male", "in_film": false}, {"name": "Fredegar Bolger", "race": "Hobbits", "culture": "Shire-hobbits (Bolger family)", "gender": "Male", "in_film": true}, {"name": "Frerin", "race": "Dwarves", "culture": "Durin's Folk, Dwarves of the Lonely Mountain", "gender": "Male", "in_film": false}, {"name": "Frodo Gamgee", "race": "Hobbits", "culture": "Shire-hobbit (Gamgee family & Gardner family)", "gender": "Male", "in_film": true}, {"name": "Frodo Gardner", "race": "Hobbits", "culture": "Shire-hobbit (Gamgee family & Gardner family)", "gender": "Male", "in_film": true}, {"name": "Frumgar", "race": "Men", "culture": "Éothéod", "gender": "Male", "in_film": false}, {"name": "Frár", "race": "Dwarf", "culture": "Durin's Folk", "gender": "Male", "in_film": false}, {"name": "Fréaláf Hildeson", "race": "Men", "culture": "Rohirrim (House of Eorl)", "gender": "Male", "in_film": false}, {"name": "Frór", "race": "Dwarves", "culture": "Durin's Folk, Dwarves of the Grey Mountains", "gender": "Male", "in_film": true}, {"name": "Fundin", "race": "Dwarves", "culture": "Durin's Folk", "gender": "Male", "in_film": false}, {"name": "Fëanor", "race": "Elves", "culture": "Ñoldor (House of Finwë)", "gender": "Other", "in_film": false}, {"name": "Fíli", "race": "Dwarves", "culture": "Durin's Folk", "gender": "Other", "in_film": true}, {"name": "Fíriel", "race": "Men", "culture": "Men of Gondor (House of Anárion)", "gender": "Female", "in_film": false}, {"name": "Galadhon", "race": "Elves", "culture": "Sindar (House of Elmo), Elves of Doriath", "gender": "Male", "in_film": false}, {"name": "Galador", "race": "Half-elf", "culture": "Gondorian", "gender": "Male", "in_film": false}, {"name": "Galadriel", "race": "Elves", "culture": "Ñoldor (House of Finarfin)Falmari (House of Olwë)", "gender": "Other", "in_film": true}, {"name": "Galathil", "race": "Elves", "culture": "Sindar (Elves of Doriath)", "gender": "Male", "in_film": false}, {"name": "Galdor", "race": "Men", "culture": "Edain (House of Hador),Men of Dor-lómin", "gender": "Male", "in_film": false}, {"name": "Galdor of the Havens", "race": "Elves", "culture": "Sindar,Elves of Lindon", "gender": "Male", "in_film": true}, {"name": "Galdor of the Tree", "race": "Elves", "culture": "Gondolindrim (House of the Tree)", "gender": "Male", "in_film": false}, {"name": "Galion", "race": "Elves", "culture": "Nandor (Elves of Mirkwood)", "gender": "Male", "in_film": true}, {"name": "Gamling", "race": "Men", "culture": "Rohirrim", "gender": "Male", "in_film": true}, {"name": "Gandalf", "race": "Ainur (Maiar)", "culture": "Istari (Wizards),Maia of Manwë and Varda", "gender": "Male", "in_film": true}, {"name": "Gandalf the Gray", "race": "Ainur (Maiar)", "culture": "Istari (Wizards),Maia of Manwë and Varda", "gender": "Male", "in_film": true}, {"name": "Gandalf the White", "race": "Ainur (Maiar)", "culture": "Istari (Wizards),Maia of Manwë and Varda", "gender": "Male", "in_film": true}, {"name": "Garulf", "race": "Men", "culture": "Rohirrim", "gender": "Male", "in_film": false}, {"name": "Gelmir", "race": "Elves", "culture": "Ñoldor, Elves of Nargothrond", "gender": "Male", "in_film": false}, {"name": "Gerontius Took", "race": "Hobbits", "culture": "Shire-hobbits (Took family)", "gender": "Male", "in_film": true}, {"name": "Gethron", "race": "Men", "culture": "Edain (House of Hador)", "gender": "Male", "in_film": false}, {"name": "Ghân-buri-Ghân", "race": "Drúedain", "gender": "Other", "in_film": false}, {"name": "Gil-Galad", "race": "Elves", "culture": "Ñoldor (House of Fingolfin) (The Silmarillion)Ñoldor (House of Finarfin), Falmari (House of Olwë) (later notes)", "gender": "Other", "in_film": true}, {"name": "Gil-galad", "race": "Elves", "culture": "Ñoldor (House of Fingolfin) (The Silmarillion)Ñoldor (House of Finarfin), Falmari (House of Olwë) (later notes)", "gender": "Other", "in_film": true}, {"name": "Gildis", "race": "Men", "culture": "Edain (House of Hador)", "gender": "Female", "in_film": false}, {"name": "Gildor", "race": "Elves", "culture": "Ñoldor (House of Finrod)", "gender": "Male", "in_film": false}, {"name": "Gildor Inglorion", "race": "Elves", "culture": "Ñoldor (House of Finrod)", "gender": "Male", "in_film": false}, {"name": "Gilfanon", "race": "Elves", "culture": "Ñoldor,Elves of Tol Eressëa", "gender": "Male", "in_film": false}, {"name": "Gilmith", "race": "Half-elven", "culture": "Dúnedain of Gondor,Silvan Elves", "gender": "Female", "in_film": false}, {"name": "Gilraen", "race": "Men", "culture": "Dúnedain of the North (House of Isildur ), Rangers of the North", "gender": "Other", "in_film": false}, {"name": "Gimilkhâd", "race": "Men", "culture": "Númenórean (House of Elros), King's Men", "gender": "Other", "in_film": false}, {"name": "Gimli", "race": "Dwarves", "culture": "Durin's Folk", "gender": "Other", "in_film": true}, {"name": "Girion", "race": "Men", "culture": "Men of Dale", "gender": "Male", "in_film": true}, {"name": "Glaurung", "race": "Dragons", "culture": "Fire-drakes, Long-worms of the North", "gender": "Male", "in_film": false}, {"name": "Glirhuin", "race": "Men", "culture": "Edain, Men of Brethil", "gender": "Male", "in_film": false}, {"name": "Gloin", "race": "Dwarves", "culture": "Durin's Folk, Dwarves of the Lonely Mountain", "gender": "Other", "in_film": true}, {"name": "Gloredhel", "race": "Men", "culture": "Edain (House of Hador)", "gender": "Female", "in_film": false}, {"name": "Glorfindel", "race": "Elves", "culture": "Ñoldor (Gondolindrim), Elves of Rivendell", "gender": "Other", "in_film": true}, {"name": "Gléowine", "race": "Men", "culture": "Rohirrim", "gender": "Male", "in_film": false}, {"name": "Glóin", "race": "Dwarves", "culture": "Durin's Folk, Dwarves of the Lonely Mountain", "gender": "Other", "in_film": true}, {"name": "Glóredhel", "race": "Men", "culture": "Edain (House of Hador)", "gender": "Female", "in_film": false}, {"name": "Goldberry", "race": "Unknown, possibly River-spirit", "gender": "Other", "in_film": false}, {"name": "Golfimbul", "race": "Orc/Goblin", "culture": "Goblins of the Ettenmoors", "gender": "Male", "in_film": false}, {"name": "Gollum", "race": "Hobbits", "culture": "Stoor-hobbits", "gender": "Male", "in_film": true}, {"name": "Gorbadoc Brandybuck", "race": "Hobbits", "culture": "Shire-hobbits (Brandybuck)", "gender": "Male", "in_film": false}, {"name": "Gorbag", "race": "Black Uruk (book)/Orc (film)", "culture": "Uruks of Minas Morgul (book)\\(Morgul Orcs) (film)", "gender": "Male", "in_film": true}, {"name": "Gorlim", "race": "Men, later Wraith", "culture": "Edain (House of Bëor)Men of Dorthonion (Ladros)", "gender": "Male", "in_film": false}, {"name": "Gorlim the Unhappy", "race": "Men, later Wraith", "culture": "Edain (House of Bëor)Men of Dorthonion (Ladros)", "gender": "Male", "in_film": false}, {"name": "Gostir", "race": "Dragons", "culture": "Dragons of Morgoth", "gender": "Male", "in_film": false}, {"name": "Gothmog", "race": "Maiar/Balrog", "culture": "Valaraukar (Balrogs of Morgoth)", "gender": "Other", "in_film": false}, {"name": "Great Goblin", "race": "Orcs/Goblins", "culture": "Orcs of the Misty Mountains", "gender": "Male", "in_film": true}, {"name": "Griffo Boffin", "race": "Hobbits", "culture": "Shire-hobbits (Boffin family)", "gender": "Male", "in_film": false}, {"name": "Grima", "race": "Men", "culture": "Rohirrim (Men of Rohan)", "gender": "Male", "in_film": true}, {"name": "Grimbeorn", "race": "Men (Skin-changer)", "culture": "Beornings", "gender": "Male", "in_film": false}, {"name": "Grimbold", "race": "Men", "culture": "Rohirrim", "gender": "Other", "in_film": true}, {"name": "Grishnákh", "race": "Orc", "gender": "Other", "in_film": true}, {"name": "Grithnir", "race": "Men", "culture": "Edain (House of Hador)", "gender": "Male", "in_film": false}, {"name": "Gríma Wormtongue", "race": "Men", "culture": "Rohirrim (Men of Rohan)", "gender": "Male", "in_film": true}, {"name": "Gróin", "race": "Dwarves", "culture": "Durin's Folk", "gender": "Male", "in_film": false}, {"name": "Grór", "race": "Dwarves", "culture": "Durin's Folk, Dwarves of the Iron Hills", "gender": "Male", "in_film": false}, {"name": "Guilin", "race": "Elves", "culture": "Ñoldor (Elves of Nargothrond)", "gender": "Male", "in_film": false}, {"name": "Gundor", "race": "Men", "culture": "Edain (House of Hador), Men of Dor-lómin", "gender": "Male", "in_film": false}, {"name": "Gwahir", "race": "Great Eagles", "culture": "Eagles of Valinor", "gender": "Male", "in_film": false}, {"name": "Gwaihir", "race": "Great Eagles", "culture": "Eagles of Valinor", "gender": "Male", "in_film": false}, {"name": "Gwindor", "race": "Elves", "culture": "Ñoldor, Elves of Nargothrond", "gender": "Other", "in_film": false}, {"name": "Hador", "race": "Men", "culture": "Edain (House of Hador)", "gender": "Male", "in_film": false}, {"name": "Halbarad", "race": "Men", "culture": "Dúnedain of the North, Rangers of the North", "gender": "Other", "in_film": false}, {"name": "Haldir of the Haladin", "race": "Men", "culture": "Edain (House of Haleth), Men of Brethil", "gender": "Male", "in_film": false}, {"name": "Haleth", "race": "Men", "culture": "Edain (House of Haleth), Men of Thargelion, Men of Brethil", "gender": "Female", "in_film": false}, {"name": "Halfred Gamgee", "race": "Hobbits", "culture": "Shire-hobbits (Gamgee family)", "gender": "Male", "in_film": false}, {"name": "Hallacar", "race": "Men", "culture": "Númenórean (House of Elros)", "gender": "Male", "in_film": false}, {"name": "Halmir", "race": "Men", "culture": "Edain (House of Haleth), Men of Brethil", "gender": "Male", "in_film": false}, {"name": "Hama", "race": "Men", "culture": "Rohirric", "gender": "Male", "in_film": true}, {"name": "Hamfast Gamgee", "race": "Hobbit", "culture": "Shire-hobbits", "gender": "Male", "in_film": true}, {"name": "Hamfast Gardner", "race": "Hobbits", "culture": "Shire-hobbits (Gardner family)", "gender": "Male", "in_film": false}, {"name": "Hamson Gamgee", "race": "Hobbits", "culture": "Shire-hobbits (Gamgee family)", "gender": "Male", "in_film": false}, {"name": "Handir", "race": "Men", "culture": "Edain (House of Haleth), Men of Brethil", "gender": "Other", "in_film": false}, {"name": "Hardang", "race": "Men", "culture": "Edain (House of Haleth), Men of Brethil", "gender": "Male", "in_film": false}, {"name": "Hareth", "race": "Men", "culture": "Edain (House of Haleth)", "gender": "Female", "in_film": false}, {"name": "Harry Goatleaf", "race": "Men", "culture": "Men of Bree", "gender": "Other", "in_film": true}, {"name": "Hathaldir", "race": "Men", "culture": "Edain (House of Bëor), Men of Dorthonion", "gender": "Other", "in_film": false}, {"name": "Hathol", "race": "Men", "culture": "Edain (House of Marach)", "gender": "Male", "in_film": false}, {"name": "Helm Hammerhand", "race": "Men", "culture": "Rohirrim (House of Eorl)", "gender": "Other", "in_film": false}, {"name": "Herucalmo", "race": "Men", "culture": "Númenóreans (King's Men) ?", "gender": "Male", "in_film": false}, {"name": "Herumor", "race": "Men", "culture": "Dunedain (Black Númenórean)", "gender": "Male", "in_film": false}, {"name": "Hildibrand Took", "race": "Hobbits", "culture": "Shire-hobbits", "gender": "Male", "in_film": false}, {"name": "Hildifons Took", "race": "Hobbits", "culture": "Shire-hobbits", "gender": "Male", "in_film": false}, {"name": "Hildigard Took", "race": "Hobbits", "culture": "Hobbit of the Shire (Took Family)", "gender": "Female", "in_film": false}, {"name": "Hildigrim Took", "race": "Hobbits", "culture": "Hobbits of the Shire (Took Family)", "gender": "Male", "in_film": false}, {"name": "Hirgon", "race": "Men", "culture": "Men of Gondor", "gender": "Male", "in_film": false}, {"name": "Hirluin the Fair", "race": "Men", "culture": "Men of Gondor", "gender": "Other", "in_film": false}, {"name": "Hob Hayward", "race": "Hobbits", "culture": "Shire-hobbits (Hayward family)", "gender": "Male", "in_film": false}, {"name": "Hobson Gamgee", "race": "Hobbits", "culture": "Shire-hobbits (Gamgee)", "gender": "Male", "in_film": false}, {"name": "Holman Greenhand", "race": "Hobbits", "culture": "Shire-hobbits (Greenhands)", "gender": "Male", "in_film": false}, {"name": "Horn", "race": "Men", "culture": "Rohirrim", "gender": "Male", "in_film": false}, {"name": "Huan", "race": "Wolfhound", "culture": "Wolves of Valinor (Great Wolves)", "gender": "Male", "in_film": false}, {"name": "Hugo Boffin", "race": "Hobbits", "culture": "Shire-hobbits (Boffin family)", "gender": "Male", "in_film": false}, {"name": "Hugo Bracegirdle", "race": "Hobbits", "culture": "Shire-hobbits (Bracegirdles)", "gender": "Male", "in_film": false}, {"name": "Hunthor", "race": "Men", "culture": "Edain (House of Haleth)", "gender": "Male", "in_film": false}, {"name": "Huor", "race": "Men", "culture": "Edain (House of Hador)", "gender": "Male", "in_film": false}, {"name": "Háma", "race": "Men", "culture": "Rohirric", "gender": "Male", "in_film": true}, {"name": "Húrin", "race": "Men", "culture": "Edain (House of Hador)Men of Dor-lómin", "gender": "Male", "in_film": false}, {"name": "Húrin Thalion", "race": "Men", "culture": "Edain (House of Hador)Men of Dor-lómin", "gender": "Male", "in_film": false}, {"name": "Ibun", "race": "Dwarves", "culture": "Petty-Dwarves", "gender": "Male", "in_film": false}, {"name": "Idril", "race": "Elves", "culture": "Ñoldor (House of Fingolfin),Gondolindrim", "gender": "Other", "in_film": false}, {"name": "Idril Celebrindal", "race": "Elves", "culture": "Ñoldor (House of Fingolfin),Gondolindrim", "gender": "Other", "in_film": false}, {"name": "Ilmarë", "race": "Ainur", "culture": "Maiar (Maia of Varda)", "gender": "Other", "in_film": false}, {"name": "Imin", "race": "Elves", "culture": "Vanyar-elves", "gender": "Male", "in_film": false}, {"name": "Iminyë", "race": "Elves", "culture": "Minyar-elves", "gender": "Female", "in_film": false}, {"name": "Imlach", "race": "Men", "culture": "Edain (House of Marach)", "gender": "Other", "in_film": false}, {"name": "Imrahil", "race": "Men", "culture": "Dúnedain (House of Dol Amroth) Men of Gondor", "gender": "Other", "in_film": false}, {"name": "Imrazôr", "race": "Men", "culture": "Gondorian", "gender": "Male", "in_film": false}, {"name": "Indis", "race": "Elves", "culture": "Vanyar (House of Finwë)", "gender": "Other", "in_film": false}, {"name": "Inglor", "race": "Elves", "culture": "Ñoldor (House of Finarfin),Falmari (House of Olwë),Elves of Nargothrond", "gender": "Male", "in_film": false}, {"name": "Ingwion", "race": "Elves", "culture": "Vanyar", "gender": "Male", "in_film": false}, {"name": "Inzilbêth", "race": "Men", "culture": "Númenóreans (House of Elros), The Faithful", "gender": "Female", "in_film": false}, {"name": "Ioreth", "race": "Men", "culture": "Men of Gondor", "gender": "Female", "in_film": false}, {"name": "Iorlas", "race": "Men", "culture": "Man of Gondor", "gender": "Male", "in_film": false}, {"name": "Irmo", "race": "Ainur", "culture": "Valar", "gender": "Other", "in_film": false}, {"name": "Isembard Took", "race": "Hobbits", "culture": "Shire-hobbits", "gender": "Male", "in_film": false}, {"name": "Isembold Took", "race": "Hobbits", "culture": "Shire-hobbits (Tooks)", "gender": "Male", "in_film": false}, {"name": "Isengar Took", "race": "Hobbits", "culture": "Shire-hobbits (Tooks)", "gender": "Male", "in_film": false}, {"name": "Isengrim Took II", "race": "Hobbits", "culture": "Shire-hobbits (Took family)", "gender": "Other", "in_film": false}, {"name": "Isengrim Took III", "race": "Hobbits", "culture": "Shire-hobbits (Tooks)", "gender": "Male", "in_film": false}, {"name": "Isildur", "race": "Men", "gender": "Other", "in_film": true}, {"name": "Isilmë", "race": "Men", "culture": "Númenóreans (House of Elros)", "gender": "Female", "in_film": false}, {"name": "Isumbras Took III", "race": "Hobbits", "culture": "Shire-hobbits (Tooks family)", "gender": "Male", "in_film": false}, {"name": "Isumbras Took IV", "race": "Hobbits", "culture": "Shire-hobbits (Tooks)", "gender": "Male", "in_film": false}, {"name": "Ivorwen", "race": "Men", "culture": "Dúnedain of the North", "gender": "Female", "in_film": false}, {"name": "Ivriniel", "race": "Men", "culture": "Dúnedain (House of Dol Amroth), Men of Gondor", "gender": "Female", "in_film": false}, {"name": "Ivy Goodenough", "race": "Hobbits", "culture": "Shire-hobbits (Goodenough family), (Boffin family)", "gender": "Female", "in_film": false}, {"name": "Jago Boffin", "race": "Hobbits", "culture": "Shire-hobbits (Boffin family)", "gender": "Male", "in_film": false}, {"name": "Jessamine Boffin", "race": "Hobbits", "culture": "Shire-hobbits (Boffin family), (Bolger family)", "gender": "Female", "in_film": false}, {"name": "Khamûl", "race": "Men (originally)", "culture": "Nazgûl (Ringwraiths), formerly Easterlings", "gender": "Male", "in_film": false}, {"name": "Kili", "race": "Dwarves", "culture": "Durin's Folk", "gender": "Other", "in_film": true}, {"name": "King Theoden", "race": "Men", "culture": "Rohirrim (House of Eorl)", "gender": "Male", "in_film": true}, {"name": "Lady Galadriel", "race": "Elves", "culture": "Ñoldor (House of Finarfin)Falmari (House of Olwë)", "gender": "Other", "in_film": true}, {"name": "Landroval", "race": "Eagle", "culture": "Great Eagles (Eagles of Valinor)", "gender": "Male", "in_film": false}, {"name": "Laura Baggins", "race": "Hobbits", "culture": "Shire-hobbits (Grubb and Baggins families)", "gender": "Female", "in_film": false}, {"name": "Legolas", "race": "Elves", "culture": "Sindar (Elves of Mirkwood)", "gender": "Other", "in_film": true}, {"name": "Legolas Greenleaf", "race": "Elves", "culture": "Sindar (Elves of Mirkwood)", "gender": "Other", "in_film": true}, {"name": "Lily Cotton", "race": "Hobbits", "culture": "Shire-hobbits (Browns Family) & (Cotton Family)", "gender": "Female", "in_film": false}, {"name": "Lindir", "race": "Elves", "culture": "Elves of Rivendell", "gender": "Other", "in_film": true}, {"name": "Lindissë", "race": "Men", "culture": "Númenóreans (House of Elros)", "gender": "Female", "in_film": false}, {"name": "Lindórië", "race": "Men", "culture": "Númenóreans (The Faithful)", "gender": "Female", "in_film": false}, {"name": "Lobelia Sackville-Baggins", "race": "Hobbit", "culture": "Shire-hobbits (Bracegirdles & Sackville-Bagginses)", "gender": "Other", "in_film": true}, {"name": "Longo Baggins", "race": "Hobbits", "culture": "Shire-hobbits (Baggins family)", "gender": "Male", "in_film": false}, {"name": "Lord Elrond", "race": "Half-elven", "gender": "Other", "in_film": true}, {"name": "Lorgan", "race": "Men", "culture": "Easterlings of Morgoth", "gender": "Male", "in_film": false}, {"name": "Lotho Sackville-Baggins", "race": "Hobbits", "culture": "Shire-hobbits (Sackville-Baggins)", "gender": "Male", "in_film": false}, {"name": "Lothíriel", "race": "Men", "culture": "Dúnedain,Men of Gondor (House of Dol Amroth),Rohirrim", "gender": "Other", "in_film": false}, {"name": "Lugdush", "race": "Uruk-hai", "culture": "Uruk-hai of Isengard", "gender": "Male", "in_film": false}, {"name": "Lungorthin", "race": "Balrog", "culture": "Valaraukar (Balrogs of Morgoth)", "gender": "Male", "in_film": false}, {"name": "Luthien", "race": "Elves (half Maiar)", "culture": "Sindar of Doriath (House of Thingol)", "gender": "Other", "in_film": false}, {"name": "Lóni", "race": "Dwarves", "culture": "Durin's Folk", "gender": "Male", "in_film": false}, {"name": "Lúthien", "race": "Elves (half Maiar)", "culture": "Sindar of Doriath (House of Thingol)", "gender": "Other", "in_film": false}, {"name": "Mablung", "race": "Elves", "culture": "Sindar (Elves of Doriath)", "gender": "Male", "in_film": false}, {"name": "Maedhros", "race": "Elves", "culture": "Ñoldor (House of Fëanor)", "gender": "Other", "in_film": false}, {"name": "Maeglin", "race": "Elves", "culture": "Avari (Moriquendi)Ñoldor (House of Fingolfin)Gondolindrim (House of the Mole)", "gender": "Male", "in_film": false}, {"name": "Maglor", "race": "Elves", "culture": "Ñoldor (House of Fëanor)", "gender": "Male", "in_film": false}, {"name": "Mahal", "race": "Ainur", "culture": "Valar (Aratar)", "gender": "Other", "in_film": false}, {"name": "Mahtan", "race": "Elves", "culture": "Ñoldor (House of Mahtan)", "gender": "Male", "in_film": false}, {"name": "Mairen", "race": "Men", "culture": "Númenóreans (House of Elros)", "gender": "Female", "in_film": false}, {"name": "Malach", "race": "Men", "culture": "Edain (House of Marach)", "gender": "Male", "in_film": false}, {"name": "Malbeth", "race": "Men", "culture": "Dúnedain of the North", "gender": "Male", "in_film": false}, {"name": "Malbeth the Seer", "race": "Men", "culture": "Dúnedain of the North", "gender": "Male", "in_film": false}, {"name": "Mandos", "race": "Ainur", "culture": "Valar (Aratar)Fëanturi", "gender": "Other", "in_film": false}, {"name": "Manwe", "race": "Ainur (Valar)", "culture": "Valar (Aratar)", "gender": "Other", "in_film": false}, {"name": "Manwendil", "race": "Men", "culture": "Númenóreans (House of Elros)", "gender": "Male", "in_film": false}, {"name": "Manwë", "race": "Ainur (Valar)", "culture": "Valar (Aratar)", "gender": "Other", "in_film": false}, {"name": "Manwë Súlimo", "race": "Ainur (Valar)", "culture": "Valar (Aratar)", "gender": "Other", "in_film": false}, {"name": "Marach", "race": "Men", "culture": "Edain (House of Marach)", "gender": "Male", "in_film": false}, {"name": "Marcho", "race": "Hobbits", "culture": "Fallohide-hobbits", "gender": "Male", "in_film": false}, {"name": "Marmadas Brandybuck", "race": "Hobbits", "culture": "Shire-hobbits, Bucklanders (Brandybuck)", "gender": "Male", "in_film": false}, {"name": "Master of Laketown", "race": "Men", "culture": "Men of Lake-town or Men of Long Lake", "gender": "Male", "in_film": true}, {"name": "Mauhúr", "race": "Uruk-hai", "gender": "Male", "in_film": true}, {"name": "May Gamgee", "race": "Hobbits", "gender": "Female", "in_film": false}, {"name": "Meleth", "race": "Men", "culture": "Edain (House of Haleth), Men of Brethil", "gender": "Female", "in_film": false}, {"name": "Melian", "race": "Ainur", "culture": "Maiar of Yavanna", "gender": "Other", "in_film": false}, {"name": "Melilot Brandybuck", "race": "Hobbits", "culture": "Bucklanders (Brandybuck family)", "gender": "Female", "in_film": false}, {"name": "Melkor", "race": "Ainur (Valar)", "culture": "Valar (Aratar),Umaiar", "gender": "Other", "in_film": false}, {"name": "Meneldil", "race": "Men", "culture": "DúnedainMen of Gondor (House of Anárion)", "gender": "Other", "in_film": false}, {"name": "Meneldor", "race": "Eagles", "culture": "Great Eagles", "gender": "Male", "in_film": false}, {"name": "Meriadoc Brandybuck", "race": "Hobbit", "culture": "Shire-hobbits, Bucklanders", "gender": "Other", "in_film": true}, {"name": "Meril-i-Turinqi", "race": "Elves", "culture": "Vanyar (Ingwi)/Teleri[1]", "gender": "Female", "in_film": false}, {"name": "Merimas Brandybuck", "race": "Hobbits", "culture": "Bucklanders (Brandybuck family)", "gender": "Male", "in_film": false}, {"name": "Merry", "race": "Hobbit", "culture": "Shire-hobbits, Bucklanders", "gender": "Other", "in_film": true}, {"name": "Merry Brandybuck", "race": "Hobbit", "culture": "Shire-hobbits, Bucklanders", "gender": "Other", "in_film": true}, {"name": "Milo Burrows", "race": "Hobbits", "culture": "Shire-hobbits (Burrows)", "gender": "Male", "in_film": false}, {"name": "Minto Burrows", "race": "Hobbits", "culture": "Shire-hobbits (Burrows)", "gender": "Male", "in_film": false}, {"name": "Mirabella Took", "race": "Hobbits", "culture": "Shire-hobbits", "gender": "Female", "in_film": false}, {"name": "Miriel", "race": "Elves", "culture": "Ñoldor (House of Finwë)", "gender": "Female", "in_film": false}, {"name": "Mithrandir", "race": "Ainur (Maiar)", "culture": "Istari (Wizards),Maia of Manwë and Varda", "gender": "Male", "in_film": true}, {"name": "Mithrellas", "race": "Elves", "culture": "Galadhrim", "gender": "Other", "in_film": false}, {"name": "Mordirith", "race": "Men", "culture": "DúnedainMen of Gondor (House of Anárion)", "gender": "Other", "in_film": false}, {"name": "Morgoth", "race": "Ainur (Valar)", "culture": "Valar (Aratar),Umaiar", "gender": "Other", "in_film": false}, {"name": "Morgoth Bauglir", "race": "Ainur (Valar)", "culture": "Valar (Aratar),Umaiar", "gender": "Other", "in_film": false}, {"name": "Morinehtar", "race": "Ainur (Maiar)", "culture": "Istari (Wizards)", "gender": "Other", "in_film": false}, {"name": "Morwen", "race": "Men", "culture": "Edain (House of Bëor), Men of Dor-lómin", "gender": "Other", "in_film": false}, {"name": "Morwen Steelsheen", "race": "Men", "culture": "Men of Gondor, Rohirrim", "gender": "Female", "in_film": false}, {"name": "Morwë", "race": "Elves", "culture": "Avari", "gender": "Other", "in_film": false}, {"name": "Mungo Baggins", "race": "Hobbits", "culture": "Shire-hobbits (Baggin family)", "gender": "Male", "in_film": false}, {"name": "Mîm", "race": "Dwarves", "culture": "Petty-dwarves", "gender": "Male", "in_film": false}, {"name": "Nahar", "race": "Horse", "gender": "Other", "in_film": false}, {"name": "Nali", "race": "Dwarves", "culture": "Durin's Folk, Dwarves of the Lonely Mountain", "gender": "Male", "in_film": false}, {"name": "Naugladur", "race": "Dwarves", "gender": "Male", "in_film": false}, {"name": "Necromancer", "race": "Ainur (Maiar)", "culture": "Maia of Melkor (earlier Aulë)", "gender": "Other", "in_film": true}, {"name": "Nellas", "race": "Elves", "culture": "Sindar-elves ?. Elves of Doriath", "gender": "Female", "in_film": false}, {"name": "Nerdanel", "race": "Elves", "culture": "Ñoldor (House of Mahtan)", "gender": "Female", "in_film": false}, {"name": "Nessa", "race": "Ainur", "culture": "Valar (Valier)", "gender": "Other", "in_film": false}, {"name": "Nessanië", "race": "Men", "culture": "Númenóreans (House of Elros)", "gender": "Female", "in_film": false}, {"name": "Nielíqui", "race": "Ainur", "culture": "Valar", "gender": "Female", "in_film": false}, {"name": "Nienna", "race": "Ainur", "culture": "Valar (Aratar)", "gender": "Other", "in_film": false}, {"name": "Nienor", "race": "Men", "culture": "Edain (House of Hador)Men of Dor-lómin", "gender": "Other", "in_film": false}, {"name": "Nimrodel", "race": "Elves", "culture": "Galadhrim", "gender": "Female", "in_film": false}, {"name": "Nob", "race": "Hobbits", "culture": "Hobbits of Bree", "gender": "Male", "in_film": false}, {"name": "Nolondil", "race": "Men", "culture": "Númenóreans (House of Elros)", "gender": "Male", "in_film": false}, {"name": "Nori", "race": "Dwarves", "culture": "Durin's Folk", "gender": "Other", "in_film": true}, {"name": "Nurwë", "race": "Elves", "culture": "Avari", "gender": "Other", "in_film": false}, {"name": "Náin I", "race": "Dwarves", "culture": "Durin's Folk, Dwarves of Khazad-dûm", "gender": "Male", "in_film": false}, {"name": "Náin II", "race": "Dwarves", "culture": "Durin's Folk, Dwarves of the Grey Mountains", "gender": "Male", "in_film": false}, {"name": "Náli", "race": "Dwarves", "culture": "Durin's Folk, Dwarves of the Lonely Mountain", "gender": "Male", "in_film": false}, {"name": "Námo", "race": "Ainur", "culture": "Valar (Aratar)Fëanturi", "gender": "Other", "in_film": false}, {"name": "Nár", "race": "Dwarves", "culture": "Dwarves of Dunland", "gender": "Male", "in_film": false}, {"name": "Númendil", "race": "Men", "culture": "Númenórean (The Faithful)", "gender": "Male", "in_film": false}, {"name": "Núneth", "race": "Men", "culture": "Númenóreans (Unnamed Minor Númenórean nobility)", "gender": "Female", "in_film": false}, {"name": "Odovacar Bolger", "race": "Hobbits", "culture": "Shire-hobbits (Bolger family)", "gender": "Male", "in_film": false}, {"name": "Ohtar", "race": "Men", "culture": "Dúnedain", "gender": "Other", "in_film": false}, {"name": "Oin", "race": "Dwarves", "culture": "Durin's Folk,Dwarves of the Thorin's Halls,Dwarves of the Lonely Mountain,Dwarves of the Khazad-dûm (briefly)", "gender": "Male", "in_film": true}, {"name": "Old Man Willow", "race": "Tree (possibly Huorn)", "culture": "The Old Forest", "gender": "Other", "in_film": false}, {"name": "Old Took", "race": "Hobbits", "culture": "Shire-hobbits (Took family)", "gender": "Male", "in_film": true}, {"name": "Olorin", "race": "Ainur (Maiar)", "culture": "Istari (Wizards),Maia of Manwë and Varda", "gender": "Male", "in_film": true}, {"name": "Olwë", "race": "Elves", "culture": "Teleri, later Falmari (House of Olwë)", "gender": "Male", "in_film": false}, {"name": "Ondoher", "race": "Men", "culture": "DúnedainMen of Gondor (House of Anárion)", "gender": "Other", "in_film": false}, {"name": "Orchaldor", "race": "Men", "culture": "Númenóreans", "gender": "Male", "in_film": false}, {"name": "Ori", "race": "Dwarves", "culture": "Durin's Folk,Dwarves of the Northern Blue Mountains,Dwarves of the Lonely Mountain", "gender": "Other", "in_film": true}, {"name": "Orodreth", "race": "Elves", "culture": "Ñoldor (House of Finarfin)Falmari (House of Olwë)Elves of Nargothrond", "gender": "Male", "in_film": false}, {"name": "Orome", "race": "Ainur", "culture": "Valar (Aratar)", "gender": "Other", "in_film": false}, {"name": "Oromendil", "race": "Men", "culture": "Númenóreans (House of Elros)", "gender": "Male", "in_film": false}, {"name": "Oromë", "race": "Ainur", "culture": "Valar (Aratar)", "gender": "Other", "in_film": false}, {"name": "Oropher", "race": "Elves", "culture": "Sindar (Elves of Doriath)", "gender": "Male", "in_film": false}, {"name": "Orophin", "race": "Elves", "culture": "Silvan Elves, Galadhrim", "gender": "Other", "in_film": false}, {"name": "Ossë", "race": "Ainur", "culture": "Maiar of Ulmo", "gender": "Male", "in_film": false}, {"name": "Ostoher", "race": "Men", "culture": "Dúnedain,Men of Gondor (House of Anárion)", "gender": "Male", "in_film": false}, {"name": "Otho", "race": "Hobbits", "culture": "Shire-hobbits (Sackville-Baggins)", "gender": "Male", "in_film": true}, {"name": "Otho Sackville-Baggins", "race": "Hobbits", "culture": "Shire-hobbits (Sackville-Baggins)", "gender": "Male", "in_film": true}, {"name": "Paladin Took II", "race": "Hobbits", "culture": "Shire-hobbits (Took family)", "gender": "Male", "in_film": false}, {"name": "Pallando", "race": "Ainur (Maiar)", "culture": "Istari (Wizards)", "gender": "Other", "in_film": false}, {"name": "Pearl Took", "race": "Hobbits", "culture": "Shire-hobbits (Took family)", "gender": "Other", "in_film": false}, {"name": "Pelendur", "race": "Men", "culture": "DúnedainMen of Gondor", "gender": "Male", "in_film": false}, {"name": "Pengolod", "race": "Elves", "culture": "Ñoldor, Gondolindrim", "gender": "Male", "in_film": false}, {"name": "Pengolodh", "race": "Elves", "culture": "Ñoldor, Gondolindrim", "gender": "Male", "in_film": false}, {"name": "Penlod", "race": "Elves", "culture": "Ñoldor, Gondolindrim (House of the Tower of Snow & House of the Pillar)", "gender": "Male", "in_film": false}, {"name": "Peony Burrows", "race": "Hobbits", "culture": "Shire-hobbits (Baggins family & Burrow family)", "gender": "Female", "in_film": false}, {"name": "Peregrin Took", "race": "Hobbits", "culture": "Shire-hobbits (Took family)", "gender": "Other", "in_film": true}, {"name": "Pippin", "race": "Hobbits", "culture": "Shire-hobbits (Took family)", "gender": "Other", "in_film": true}, {"name": "Pippin Took", "race": "Hobbits", "culture": "Shire-hobbits (Took family)", "gender": "Other", "in_film": true}, {"name": "Ponto Baggins", "race": "Hobbits", "culture": "Shire-hobbits (Baggins family)", "gender": "Male", "in_film": false}, {"name": "Primula Brandybuck", "race": "Hobbits", "culture": "Shire-hobbits (Brandybuck & Baggins family)", "gender": "Female", "in_film": false}, {"name": "Prince Imrahil", "race": "Men", "culture": "Dúnedain (House of Dol Amroth) Men of Gondor", "gender": "Other", "in_film": false}, {"name": "Quickbeam", "race": "Ents", "gender": "Male", "in_film": false}, {"name": "Radagast", "race": "Ainur (Maiar)", "culture": "Istari (Wizards)Maiar of Yavanna", "gender": "Other", "in_film": true}, {"name": "Ragnir", "race": "Men", "culture": "Edain (House of Hador)", "gender": "Male", "in_film": false}, {"name": "Rian", "race": "Men", "culture": "Edain (House of Bëor)Men of Dorthonion", "gender": "Other", "in_film": false}, {"name": "Robin Smallburrow", "race": "Hobbits", "culture": "Shire-hobbits (Smallburrow family)", "gender": "Other", "in_film": true}, {"name": "Rog", "race": "Elves", "culture": "Gondolindrim (House of the Hammer of Wrath)", "gender": "Male", "in_film": false}, {"name": "Rorimac Brandybuck", "race": "Hobbits", "culture": "Shire-hobbits (Brandybuck)", "gender": "Male", "in_film": false}, {"name": "Rosamunda Took", "race": "Men", "culture": "Shire-hobbits (Took and Bolger families)", "gender": "Female", "in_film": false}, {"name": "Rosie", "race": "Hobbits", "culture": "Shire-hobbits (Cotton family/Gamgee family)", "gender": "Other", "in_film": true}, {"name": "Rosie Cotton", "race": "Hobbits", "culture": "Shire-hobbits (Cotton family/Gamgee family)", "gender": "Other", "in_film": true}, {"name": "Rosie Gamgee", "race": "Hobbits", "culture": "Shire-hobbits (Cotton family/Gamgee family)", "gender": "Other", "in_film": true}, {"name": "Roäc", "race": "Raven", "culture": "Ravens of Ravenhill", "gender": "Male", "in_film": false}, {"name": "Rudigar Bolger", "race": "Hobbits", "culture": "Shire-hobbits (Bolger family)", "gender": "Male", "in_film": false}, {"name": "Rufus Burrows", "race": "Hobbit", "culture": "Shire-hobbits (Burrows family)", "gender": "Male", "in_film": false}, {"name": "Rómestámo", "race": "Ainur (Maiar)", "culture": "Istari (Wizards)", "gender": "Other", "in_film": false}, {"name": "Rúmil of Tirion", "race": "Elves", "culture": "Ñoldor,Lambengolmor", "gender": "Male", "in_film": false}, {"name": "Sador Labadal", "race": "Men", "culture": "Edain (House of Hador)", "gender": "Male", "in_film": false}, {"name": "Saeros", "race": "Elves", "culture": "Nandor (Elves of Doriath)", "gender": "Male", "in_film": false}, {"name": "Salgant", "race": "Elves", "culture": "ÑoldorGondolindrim (House of the Harp)", "gender": "Male", "in_film": false}, {"name": "Salmar", "race": "Ainur", "culture": "Maiar of Ulmo", "gender": "Male", "in_film": false}, {"name": "Sam", "race": "Hobbits", "culture": "Shire-hobbits (Gamgee family)", "gender": "Other", "in_film": true}, {"name": "Sam Gamgee", "race": "Hobbits", "culture": "Shire-hobbits (Gamgee family)", "gender": "Other", "in_film": true}, {"name": "Samwise", "race": "Hobbits", "culture": "Shire-hobbits (Gamgee family)", "gender": "Other", "in_film": true}, {"name": "Samwise Gamgee", "race": "Hobbits", "culture": "Shire-hobbits (Gamgee family)", "gender": "Other", "in_film": true}, {"name": "Samwise the Brave", "race": "Hobbits", "culture": "Shire-hobbits (Gamgee family)", "gender": "Other", "in_film": true}, {"name": "Sancho Proudfoot", "race": "Hobbits", "culture": "Shire-hobbit (Proudfoot family)", "gender": "Male", "in_film": false}, {"name": "Saradas Brandybuck", "race": "Hobbits", "culture": "Shire-hobbits, Bucklanders (Brandybuck)", "gender": "Male", "in_film": false}, {"name": "Saradoc Brandybuck", "race": "Hobbits", "culture": "Shire-hobbits (Brandybuck)", "gender": "Other", "in_film": false}, {"name": "Saruman", "race": "Ainur", "culture": "Maiar of Aulë (Wizards)", "gender": "Male", "in_film": true}, {"name": "Sauron", "race": "Ainur (Maiar)", "culture": "Maia of Melkor (earlier Aulë)", "gender": "Other", "in_film": true}, {"name": "Scatha", "race": "Dragons", "culture": "Long-worms", "gender": "Male", "in_film": false}, {"name": "Seredic Brandybuck", "race": "Hobbits", "culture": "Shire-hobbits (Brandybuck family)", "gender": "Male", "in_film": false}, {"name": "Sharkey", "race": "Ainur", "culture": "Maiar of Aulë (Wizards)", "gender": "Male", "in_film": true}, {"name": "Shelob", "race": "Spiders", "culture": "Descendant of Ungoliant[2]", "gender": "Female", "in_film": true}, {"name": "Sigismond Took", "race": "Hobbits", "culture": "Shire-hobbits (Took family)", "gender": "Male", "in_film": false}, {"name": "Silmariën", "race": "Men", "culture": "Númenóreans (House of Elros)", "gender": "Female", "in_film": false}, {"name": "Smaug", "race": "Dragons", "culture": "Urulókë; fire-drake[3]", "gender": "Male", "in_film": true}, {"name": "Sméagol", "race": "Hobbits", "culture": "Stoor-hobbits", "gender": "Male", "in_film": true}, {"name": "Soronto", "race": "Men", "culture": "Númenoreans (House of Elros)", "gender": "Male", "in_film": false}, {"name": "Tar-Alcarin", "race": "Men", "culture": "Númenóreans (House of Elros)King's Men", "gender": "Male", "in_film": false}, {"name": "Tar-Aldarion", "race": "Men", "culture": "Númenóreans (House of Elros)", "gender": "Male", "in_film": false}, {"name": "Tar-Ancalimon", "race": "Men", "culture": "Númenórean (House of Elros), King's Men", "gender": "Male", "in_film": false}, {"name": "Tar-Ancalimë", "race": "Men", "culture": "Númenóreans (House of Elros)", "gender": "Female", "in_film": false}, {"name": "Tar-Anducal", "race": "Men", "culture": "Númenóreans (King's Men) ?", "gender": "Male", "in_film": false}, {"name": "Tar-Anárion", "race": "Men", "culture": "Númenóreans (House of Elros)", "gender": "Male", "in_film": false}, {"name": "Tar-Ardamin", "race": "Men", "culture": "Númenóreans (King's Men)", "gender": "Male", "in_film": false}, {"name": "Tar-Atanamir", "race": "Men", "culture": "Númenóreans (House of Elros)", "gender": "Male", "in_film": false}, {"name": "Tar-Calmacil", "race": "Men", "culture": "Númenórean (King's Men)", "gender": "Male", "in_film": false}, {"name": "Tar-Ciryatan", "race": "Men", "culture": "Númenórean (House of Elros)", "gender": "Male", "in_film": false}, {"name": "Tar-Elendil", "race": "Men", "culture": "Númenóreans (House of Elros)", "gender": "Male", "in_film": false}, {"name": "Tar-Meneldur", "race": "Men", "culture": "Númenóreans (House of Elros)", "gender": "Male", "in_film": false}, {"name": "Tar-Minastir", "race": "Men", "culture": "Númenóreans (House of Elros)", "gender": "Male", "in_film": false}, {"name": "Tar-Míriel", "race": "Men", "culture": "Númenóreans (House of Elros, The Faithful)", "gender": "Female", "in_film": false}, {"name": "Tar-Palantir", "race": "Men", "culture": "Númenóreans (House of Elros), The Faithful", "gender": "Male", "in_film": false}, {"name": "Tar-Telemmaitë", "race": "Men", "culture": "Númenóreans (House of Elros), King's Men", "gender": "Male", "in_film": false}, {"name": "Tar-Telperiën", "race": "Men", "culture": "Númenóreans (House of Elros)", "gender": "Female", "in_film": false}, {"name": "Tar-Vanimeldë", "race": "Men", "culture": "Númenórean (House of Elros)", "gender": "Female", "in_film": false}, {"name": "Tarannon Falastur", "race": "Men", "culture": "Dúnedain,Men of Gondor (House of Anárion)", "gender": "Male", "in_film": false}, {"name": "Tarcil", "race": "Men", "culture": "Dúnedain of the North (House of Isildur)", "gender": "Male", "in_film": false}, {"name": "Tarondor of Arnor", "race": "Men", "culture": "Dúnedain of the North (House of Isildur)", "gender": "Male", "in_film": false}, {"name": "Tata", "race": "Elves", "culture": "Tatyar-elves", "gender": "Male", "in_film": false}, {"name": "Tatië", "race": "Elves", "culture": "Tatyar-elves", "gender": "Female", "in_film": false}, {"name": "Ted Sandyman", "race": "Hobbits", "culture": "Shire-hobbits", "gender": "Male", "in_film": true}, {"name": "Telchar", "race": "Dwarves", "culture": "Dwarves of Nogrod", "gender": "Male", "in_film": false}, {"name": "Telumehtar", "race": "Men", "culture": "Dúnedain (House of Anárion)Men of Gondor", "gender": "Male", "in_film": false}, {"name": "The Great Goblin", "race": "Orcs/Goblins", "culture": "Orcs of the Misty Mountains", "gender": "Male", "in_film": true}, {"name": "The Witch King of Angmar", "race": "Man (Wraith)", "culture": "Possibly Númenórean[1] (formerly)Ringwraith (later)", "gender": "Other", "in_film": true}, {"name": "Thengel", "race": "Men", "culture": "Rohirrim (House of Eorl)", "gender": "Other", "in_film": false}, {"name": "Theoden", "race": "Men", "culture": "Rohirrim (House of Eorl)", "gender": "Male", "in_film": true}, {"name": "Theodred", "race": "Men", "culture": "Rohirrim (House of Eorl)", "gender": "Male", "in_film": true}, {"name": "Thingol", "race": "Elves", "culture": "Teleri (Sindar)(House of Thingol)Elves of Doriath", "gender": "Other", "in_film": false}, {"name": "Thorin I", "race": "Dwarves", "culture": "Durin's Folk", "gender": "Male", "in_film": false}, {"name": "Thorin II Oakenshield", "race": "Dwarves", "culture": "Durin's Folk", "gender": "Other", "in_film": true}, {"name": "Thorin III Stonehelm", "race": "Dwarves", "culture": "Durin's Folk", "gender": "Other", "in_film": false}, {"name": "Thorin Oakenshield", "race": "Dwarves", "culture": "Durin's Folk", "gender": "Other", "in_film": true}, {"name": "Thorondor", "race": "Great Eagles", "culture": "Eagles of Manwë", "gender": "Male", "in_film": false}, {"name": "Thranduil", "race": "Elves", "culture": "Sindar (Elves of Mirkwood)", "gender": "Other", "in_film": true}, {"name": "Thror", "race": "Dwarves", "culture": "Durin's Folk", "gender": "Male", "in_film": true}, {"name": "Thráin I", "race": "Dwarves", "culture": "Durin's Folk, Dwarves of Lonely Mountain", "gender": "Male", "in_film": false}, {"name": "Thráin II", "race": "Dwarves", "culture": "Durin's Folk", "gender": "Male", "in_film": true}, {"name": "Thrór", "race": "Dwarves", "culture": "Durin's Folk", "gender": "Male", "in_film": true}, {"name": "Thuringwethil", "race": "Ainur", "culture": "Maiar (Vampire)", "gender": "Female", "in_film": false}, {"name": "Théoden", "race": "Men", "culture": "Rohirrim (House of Eorl)", "gender": "Male", "in_film": true}, {"name": "Théoden King", "race": "Men", "culture": "Rohirrim (House of Eorl)", "gender": "Male", "in_film": true}, {"name": "Théodred", "race": "Men", "culture": "Rohirrim (House of Eorl)", "gender": "Male", "in_film": true}, {"name": "Théodwyn", "race": "Men", "culture": "Rohan", "gender": "Female", "in_film": false}, {"name": "Tilion", "race": "Ainur", "culture": "Maiar", "gender": "Male", "in_film": false}, {"name": "Tindómiel", "race": "Men", "culture": "Númenóreans (House of Elros)", "gender": "Female", "in_film": false}, {"name": "Tolman Cotton", "race": "Hobbits", "culture": "Shire-hobbits (Cotton family)", "gender": "Male", "in_film": false}, {"name": "Tom", "race": "Stone-trolls", "gender": "Other", "in_film": true}, {"name": "Tom Bombadil", "race": "Unknown", "gender": "Other", "in_film": false}, {"name": "Treebeard", "race": "Ents, Onodrim", "gender": "Other", "in_film": true}, {"name": "Tulkas", "race": "Ainur", "culture": "Valar", "gender": "Other", "in_film": false}, {"name": "Tuor", "race": "Men", "culture": "Edain (House of Hador)EldarGondolindrim", "gender": "Other", "in_film": false}, {"name": "Turgon", "race": "Elves", "culture": "Ñoldor (House of Fingolfin)Gondolindrim", "gender": "Male", "in_film": false}, {"name": "Túrin II", "race": "Men", "culture": "Men of Gondor (House of Húrin)", "gender": "Male", "in_film": false}, {"name": "Túrin Turambar", "race": "Men", "culture": "Edain (House of Hador)", "gender": "Male", "in_film": false}, {"name": "Uglúk", "race": "Uruk-hai", "gender": "Other", "in_film": true}, {"name": "Uin", "race": "Right Whale", "gender": "Male", "in_film": false}, {"name": "Uinen", "race": "Ainur", "culture": "Maiar (Maia of Ulmo)", "gender": "Other", "in_film": false}, {"name": "Ulbar", "race": "Men", "culture": "Númenóreans", "gender": "Male", "in_film": false}, {"name": "Uldor", "race": "Men", "culture": "Easterlings of Morgoth", "gender": "Male", "in_film": false}, {"name": "Ulfang", "race": "Men", "culture": "Easterlings", "gender": "Male", "in_film": false}, {"name": "Ulfast", "race": "Men", "culture": "Easterlings of Morgoth", "gender": "Male", "in_film": false}, {"name": "Ulmo", "race": "Ainur", "culture": "Valar (Aratar)", "gender": "Other", "in_film": false}, {"name": "Ulwarth", "race": "Men", "culture": "Easterlings of Morgoth", "gender": "Male", "in_film": false}, {"name": "Urwen", "race": "Men", "culture": "Edain (House of Hador), Men of Dor-lómin", "gender": "Female", "in_film": false}, {"name": "Urwen Lalaith", "race": "Men", "culture": "Edain (House of Hador), Men of Dor-lómin", "gender": "Female", "in_film": false}, {"name": "Vairë", "race": "Ainur", "culture": "Valier", "gender": "Other", "in_film": false}, {"name": "Valacar", "race": "Men", "culture": "Dúnedain, Men of Gondor", "gender": "Male", "in_film": false}, {"name": "Valandil", "race": "Men", "culture": "Dúnedain of the North (House of Isildur)", "gender": "Male", "in_film": false}, {"name": "Varda", "race": "Ainur", "culture": "Valar (Aratar) (Leader, Queen)", "gender": "Other", "in_film": false}, {"name": "Vardilmë", "race": "Men", "culture": "Númenóreans (House of Elros)", "gender": "Female", "in_film": false}, {"name": "Vidumavi", "race": "Men", "culture": "Northmen,Men of Gondor", "gender": "Female", "in_film": false}, {"name": "Vigo Boffin", "race": "Hobbits", "culture": "Shire-hobbits (Boffin family", "gender": "Male", "in_film": false}, {"name": "Voronwë", "race": "Elves", "culture": "Ñoldor (House of Fingolfin)Gondolindrim", "gender": "Male", "in_film": false}, {"name": "Vána", "race": "Ainur", "culture": "Valier", "gender": "Other", "in_film": false}, {"name": "Vëantur", "race": "Men", "culture": "Númenóreans", "gender": "Male", "in_film": false}, {"name": "Watcher in the Water", "race": "Unknown", "gender": "Other", "in_film": false}, {"name": "Widow Rumble", "race": "Hobbit", "culture": "Shire-hobbits", "gender": "Female", "in_film": false}, {"name": "Will Whitfoot", "race": "Hobbit", "culture": "Shire-hobbits", "gender": "Male", "in_film": false}, {"name": "Windfola", "race": "Horses", "gender": "Other", "in_film": false}, {"name": "Witch King", "race": "Man (Wraith)", "culture": "Possibly Númenórean[1] (formerly)Ringwraith (later)", "gender": "Other", "in_film": true}, {"name": "Witch-King of Angmar", "race": "Man (Wraith)", "culture": "Possibly Númenórean[1] (formerly)Ringwraith (later)", "gender": "Other", "in_film": true}, {"name": "Wormtongue", "race": "Men", "culture": "Rohirrim (Men of Rohan)", "gender": "Male", "in_film": true}, {"name": "Wulf", "race": "Men", "culture": "Dunlendings", "gender": "Male", "in_film": false}, {"name": "Yavanna", "race": "Ainur (Valar)", "culture": "Valier (Aratar)", "gender": "Other", "in_film": false}, {"name": "Yávien", "race": "Men", "culture": "Númenóreans (House of Elros)", "gender": "Female", "in_film": false}, {"name": "Zamîn", "race": "Men", "culture": "Númenóreans", "gender": "Female", "in_film": false}, {"name": "elvenking", "race": "Elves", "culture": "Sindar (Elves of Mirkwood)", "gender": "Other", "in_film": true}, {"name": "fili", "race": "Dwarves", "culture": "Durin's Folk", "gender": "Other", "in_film": true}, {"name": "findis", "race": "Elves", "culture": "Ñoldor (House of Finwë)", "gender": "Female", "in_film": false}, {"name": "gandalf the grey", "race": "Ainur (Maiar)", "culture": "Istari (Wizards),Maia of Manwë and Varda", "gender": "Male", "in_film": true}, {"name": "huan", "race": "Wolfhound", "culture": "Wolves of Valinor (Great Wolves)", "gender": "Male", "in_film": false}, {"name": "kili", "race": "Dwarves", "culture": "Durin's Folk", "gender": "Other", "in_film": true}, {"name": "legolas", "race": "Elves", "culture": "Sindar (Elves of Mirkwood)", "gender": "Other", "in_film": true}, {"name": "maglor", "race": "Elves", "culture": "Ñoldor (House of Fëanor)", "gender": "Male", "in_film": false}, {"name": "manwe", "race": "Ainur (Valar)", "culture": "Valar (Aratar)", "gender": "Other", "in_film": false}, {"name": "osse", "race": "Ainur", "culture": "Maiar of Ulmo", "gender": "Male", "in_film": false}, {"name": "radagast the brown", "race": "Ainur (Maiar)", "culture": "Istari (Wizards)Maiar of Yavanna", "gender": "Other", "in_film": true}, {"name": "the Gaffer", "race": "Hobbit", "culture": "Shire-hobbits", "gender": "Male", "in_film": true}, {"name": "the Witch King", "race": "Man (Wraith)", "culture": "Possibly Númenórean[1] (formerly)Ringwraith (later)", "gender": "Other", "in_film": true}, {"name": "uinen", "race": "Ainur", "culture": "Maiar (Maia of Ulmo)", "gender": "Other", "in_film": false}, {"name": "Ælfwine", "race": "Man", "culture": "Mannish/Englishman", "gender": "Male", "in_film": false}, {"name": "Éomer", "race": "Men", "culture": "Rohirrim (House of Eorl)", "gender": "Other", "in_film": true}, {"name": "Éomund", "race": "Men", "culture": "Rohirrim", "gender": "Male", "in_film": false}, {"name": "Éothain", "race": "Men", "culture": "Rohirrim", "gender": "Other", "in_film": false}, {"name": "Éowyn", "race": "Men", "culture": "Rohirrim (House of Eorl)", "gender": "Other", "in_film": true}, {"name": "Írildë", "race": "Men", "culture": "Númenóreans (House of Elros)", "gender": "Female", "in_film": false}, {"name": "Írimë", "race": "Elves", "culture": "Ñoldor (House of Finwë)", "gender": "Female", "in_film": false}, {"name": "Óin", "race": "Dwarves", "culture": "Durin's Folk,Dwarves of the Thorin's Halls,Dwarves of the Lonely Mountain,Dwarves of the Khazad-dûm (briefly)", "gender": "Male", "in_film": true}, {"name": "Bregalad", "race": "Ents", "gender": "Male", "in_film": false}, {"name": "Dáin II Ironfoot", "race": "Dwarves", "culture": "Durin's Folk (Dwarves of the Iron Hills)", "gender": "Male", "in_film": true}, {"name": "Estella Bolger", "race": "Hobbits", "culture": "Shire-hobbits (Bolger/Brandybuck)", "gender": "Female", "in_film": false}, {"name": "Fladrif", "race": "Ents", "culture": "Ents of Fangorn Forest", "gender": "Male", "in_film": false}, {"name": "Lenwë", "race": "Elves", "culture": "Teleri/Nandor", "gender": "Male", "in_film": false}, {"name": "Master of Lake-town", "race": "Men", "culture": "Men of Lake-town or Men of Long Lake", "gender": "Male", "in_film": true}, {"name": "Niënor", "race": "Men", "culture": "Edain (House of Hador)Men of Dor-lómin", "gender": "Other", "in_film": false}, {"name": "Náin (father of Dáin II Ironfoot)", "race": "Dwarves", "culture": "Durin's Folk", "gender": "Male", "in_film": false}, {"name": "Witch-king of Angmar", "race": "Man (Wraith)", "culture": "Possibly Númenórean[1] (formerly)Ringwraith (later)", "gender": "Other", "in_film": true}, {"name": "thranduil", "race": "Elves", "culture": "Sindar (Elves of Mirkwood)", "gender": "Other", "in_film": true}, {"name": "Haldir (Lorien)", "race": "Elves", "culture": "Nandor (Silvan Elves), Galadhrim", "gender": "Other", "in_film": true}]
